{
"meta":{"test_sets":[],"test_metrics":[],"learn_metrics":[{"best_value":"Min","name":"RMSE"}],"launch_mode":"Train","parameters":"","iteration_count":1000,"learn_sets":["learn"],"name":"experiment"},
"iterations":[
{"learn":[43.190953],"iteration":0,"passed_time":0.15331022,"remaining_time":153.1569098},
{"learn":[43.11496109],"iteration":1,"passed_time":0.1580835447,"remaining_time":78.8836888},
{"learn":[43.01376248],"iteration":2,"passed_time":0.1624137732,"remaining_time":53.97551062},
{"learn":[42.95610529],"iteration":3,"passed_time":0.1660804114,"remaining_time":41.35402243},
{"learn":[42.86568032],"iteration":4,"passed_time":0.1697229591,"remaining_time":33.77486887},
{"learn":[42.76692391],"iteration":5,"passed_time":0.1740152763,"remaining_time":28.82853078},
{"learn":[42.68500963],"iteration":6,"passed_time":0.1775853236,"remaining_time":25.19174663},
{"learn":[42.60676433],"iteration":7,"passed_time":0.1837148777,"remaining_time":22.78064483},
{"learn":[42.53589612],"iteration":8,"passed_time":0.1872764852,"remaining_time":20.62122187},
{"learn":[42.47355984],"iteration":9,"passed_time":0.1914277857,"remaining_time":18.95135078},
{"learn":[42.38402656],"iteration":10,"passed_time":0.195127066,"remaining_time":17.54369712},
{"learn":[42.29208708],"iteration":11,"passed_time":0.1976956651,"remaining_time":16.27694309},
{"learn":[42.22796054],"iteration":12,"passed_time":0.2009818883,"remaining_time":15.25916336},
{"learn":[42.11393229],"iteration":13,"passed_time":0.2040095595,"remaining_time":14.36810183},
{"learn":[42.05655277],"iteration":14,"passed_time":0.2081195505,"remaining_time":13.66651715},
{"learn":[41.95418281],"iteration":15,"passed_time":0.2103898725,"remaining_time":12.93897716},
{"learn":[41.89508631],"iteration":16,"passed_time":0.2133490098,"remaining_time":12.33659274},
{"learn":[41.80723514],"iteration":17,"passed_time":0.2160096141,"remaining_time":11.7845245},
{"learn":[41.71909143],"iteration":18,"passed_time":0.2184779935,"remaining_time":11.28036377},
{"learn":[41.62253277],"iteration":19,"passed_time":0.2207258574,"remaining_time":10.81556701},
{"learn":[41.52908388],"iteration":20,"passed_time":0.223421077,"remaining_time":10.41567783},
{"learn":[41.44944135],"iteration":21,"passed_time":0.2266460642,"remaining_time":10.07544777},
{"learn":[41.39437157],"iteration":22,"passed_time":0.23010369,"remaining_time":9.77440457},
{"learn":[41.32588029],"iteration":23,"passed_time":0.233178154,"remaining_time":9.482578261},
{"learn":[41.23995212],"iteration":24,"passed_time":0.2364955407,"remaining_time":9.223326089},
{"learn":[41.15070349],"iteration":25,"passed_time":0.2399657783,"remaining_time":8.989487233},
{"learn":[41.08665349],"iteration":26,"passed_time":0.2431539176,"remaining_time":8.762546735},
{"learn":[41.02951141],"iteration":27,"passed_time":0.2457980863,"remaining_time":8.532704996},
{"learn":[40.95775637],"iteration":28,"passed_time":0.2492436692,"remaining_time":8.345365613},
{"learn":[40.89227823],"iteration":29,"passed_time":0.2531746837,"remaining_time":8.18598144},
{"learn":[40.79620084],"iteration":30,"passed_time":0.2553673277,"remaining_time":7.982288405},
{"learn":[40.74805882],"iteration":31,"passed_time":0.2593483452,"remaining_time":7.845287442},
{"learn":[40.7142679],"iteration":32,"passed_time":0.2623881101,"remaining_time":7.68876674},
{"learn":[40.64982395],"iteration":33,"passed_time":0.2648585808,"remaining_time":7.525099677},
{"learn":[40.60076461],"iteration":34,"passed_time":0.2679241967,"remaining_time":7.387052851},
{"learn":[40.48622647],"iteration":35,"passed_time":0.2727363182,"remaining_time":7.303272522},
{"learn":[40.42415925],"iteration":36,"passed_time":0.2761765602,"remaining_time":7.188054796},
{"learn":[40.34147374],"iteration":37,"passed_time":0.2785993912,"remaining_time":7.052963536},
{"learn":[40.28952644],"iteration":38,"passed_time":0.2817123304,"remaining_time":6.941680757},
{"learn":[40.19477919],"iteration":39,"passed_time":0.284003793,"remaining_time":6.816091031},
{"learn":[40.14077157],"iteration":40,"passed_time":0.2867563145,"remaining_time":6.707300136},
{"learn":[40.10464416],"iteration":41,"passed_time":0.2890867827,"remaining_time":6.593931853},
{"learn":[40.05654441],"iteration":42,"passed_time":0.2914731985,"remaining_time":6.486973278},
{"learn":[39.98351196],"iteration":43,"passed_time":0.2933603882,"remaining_time":6.373921161},
{"learn":[39.91916735],"iteration":44,"passed_time":0.2959365598,"remaining_time":6.280431435},
{"learn":[39.87738366],"iteration":45,"passed_time":0.2980494341,"remaining_time":6.181286089},
{"learn":[39.81275125],"iteration":46,"passed_time":0.3006611457,"remaining_time":6.096384506},
{"learn":[39.75668069],"iteration":47,"passed_time":0.3035352425,"remaining_time":6.020115642},
{"learn":[39.69253597],"iteration":48,"passed_time":0.3059657186,"remaining_time":5.93823262},
{"learn":[39.6352448],"iteration":49,"passed_time":0.3083678057,"remaining_time":5.858988308},
{"learn":[39.54266025],"iteration":50,"passed_time":0.311261549,"remaining_time":5.791906078},
{"learn":[39.46543955],"iteration":51,"passed_time":0.3134652964,"remaining_time":5.714713481},
{"learn":[39.42167908],"iteration":52,"passed_time":0.3157809015,"remaining_time":5.642349316},
{"learn":[39.35543824],"iteration":53,"passed_time":0.3184927028,"remaining_time":5.579520312},
{"learn":[39.27469806],"iteration":54,"passed_time":0.3214077009,"remaining_time":5.522368679},
{"learn":[39.17163489],"iteration":55,"passed_time":0.3238063179,"remaining_time":5.458449359},
{"learn":[39.0931678],"iteration":56,"passed_time":0.3259954595,"remaining_time":5.393223127},
{"learn":[39.03283237],"iteration":57,"passed_time":0.3281738383,"remaining_time":5.329995787},
{"learn":[38.9713939],"iteration":58,"passed_time":0.3302621034,"remaining_time":5.267400665},
{"learn":[38.9378759],"iteration":59,"passed_time":0.3331115314,"remaining_time":5.218747326},
{"learn":[38.82560671],"iteration":60,"passed_time":0.3362935371,"remaining_time":5.176715268},
{"learn":[38.78626121],"iteration":61,"passed_time":0.3390194719,"remaining_time":5.129036527},
{"learn":[38.70910218],"iteration":62,"passed_time":0.3410773385,"remaining_time":5.072848669},
{"learn":[38.64851042],"iteration":63,"passed_time":0.3434359592,"remaining_time":5.022750904},
{"learn":[38.61976207],"iteration":64,"passed_time":0.3465381715,"remaining_time":4.984818313},
{"learn":[38.5639644],"iteration":65,"passed_time":0.3491633905,"remaining_time":4.941191011},
{"learn":[38.48807769],"iteration":66,"passed_time":0.3520534406,"remaining_time":4.902475524},
{"learn":[38.42484571],"iteration":67,"passed_time":0.3540702796,"remaining_time":4.852845597},
{"learn":[38.36487059],"iteration":68,"passed_time":0.356762442,"remaining_time":4.813707733},
{"learn":[38.29703635],"iteration":69,"passed_time":0.3588844695,"remaining_time":4.768036523},
{"learn":[38.22762087],"iteration":70,"passed_time":0.3610870777,"remaining_time":4.724646411},
{"learn":[38.15127075],"iteration":71,"passed_time":0.3635565816,"remaining_time":4.685840385},
{"learn":[38.03834886],"iteration":72,"passed_time":0.3660067897,"remaining_time":4.64778485},
{"learn":[37.99273019],"iteration":73,"passed_time":0.3679163493,"remaining_time":4.603926209},
{"learn":[37.9448129],"iteration":74,"passed_time":0.3698304898,"remaining_time":4.561242707},
{"learn":[37.89787122],"iteration":75,"passed_time":0.3722063777,"remaining_time":4.525245961},
{"learn":[37.84440829],"iteration":76,"passed_time":0.374505636,"remaining_time":4.489203923},
{"learn":[37.81063105],"iteration":77,"passed_time":0.3766901552,"remaining_time":4.452670809},
{"learn":[37.77661573],"iteration":78,"passed_time":0.3790811075,"remaining_time":4.419413924},
{"learn":[37.71349915],"iteration":79,"passed_time":0.3815008343,"remaining_time":4.387259594},
{"learn":[37.64413988],"iteration":80,"passed_time":0.3838424013,"remaining_time":4.354952676},
{"learn":[37.61365293],"iteration":81,"passed_time":0.3859344738,"remaining_time":4.3205835},
{"learn":[37.5521324],"iteration":82,"passed_time":0.388175742,"remaining_time":4.288640427},
{"learn":[37.51515424],"iteration":83,"passed_time":0.3902052894,"remaining_time":4.255095775},
{"learn":[37.46148984],"iteration":84,"passed_time":0.392835373,"remaining_time":4.22875725},
{"learn":[37.40421162],"iteration":85,"passed_time":0.3962528157,"remaining_time":4.211338065},
{"learn":[37.33985989],"iteration":86,"passed_time":0.3989061235,"remaining_time":4.186221732},
{"learn":[37.29951143],"iteration":87,"passed_time":0.4012826084,"remaining_time":4.158747033},
{"learn":[37.22318079],"iteration":88,"passed_time":0.4034643481,"remaining_time":4.129842934},
{"learn":[37.15058219],"iteration":89,"passed_time":0.4055952784,"remaining_time":4.101018926},
{"learn":[37.09532743],"iteration":90,"passed_time":0.4081230142,"remaining_time":4.076745274},
{"learn":[37.04752676],"iteration":91,"passed_time":0.4115586241,"remaining_time":4.061904682},
{"learn":[37.00066439],"iteration":92,"passed_time":0.4144047365,"remaining_time":4.041560172},
{"learn":[36.92213742],"iteration":93,"passed_time":0.4174599876,"remaining_time":4.02360371},
{"learn":[36.88787746],"iteration":94,"passed_time":0.4197550371,"remaining_time":3.998719038},
{"learn":[36.8248547],"iteration":95,"passed_time":0.4220124393,"remaining_time":3.97395047},
{"learn":[36.74545691],"iteration":96,"passed_time":0.4240240731,"remaining_time":3.947358123},
{"learn":[36.69604747],"iteration":97,"passed_time":0.4263743669,"remaining_time":3.924384479},
{"learn":[36.62098802],"iteration":98,"passed_time":0.4290815001,"remaining_time":3.905075067},
{"learn":[36.56185674],"iteration":99,"passed_time":0.4313869071,"remaining_time":3.882482164},
{"learn":[36.48466739],"iteration":100,"passed_time":0.4335300977,"remaining_time":3.858847108},
{"learn":[36.42684583],"iteration":101,"passed_time":0.4353893524,"remaining_time":3.83313371},
{"learn":[36.39200661],"iteration":102,"passed_time":0.4373898392,"remaining_time":3.809113454},
{"learn":[36.33647367],"iteration":103,"passed_time":0.4397905763,"remaining_time":3.788964965},
{"learn":[36.29223977],"iteration":104,"passed_time":0.4423478928,"remaining_time":3.770489182},
{"learn":[36.23865438],"iteration":105,"passed_time":0.4446489608,"remaining_time":3.750152556},
{"learn":[36.17102079],"iteration":106,"passed_time":0.4468224237,"remaining_time":3.729088078},
{"learn":[36.11797324],"iteration":107,"passed_time":0.4487702119,"remaining_time":3.706509528},
{"learn":[36.06396814],"iteration":108,"passed_time":0.4510242626,"remaining_time":3.686813009},
{"learn":[36.00824007],"iteration":109,"passed_time":0.4533395704,"remaining_time":3.667929251},
{"learn":[35.95533581],"iteration":110,"passed_time":0.455654811,"remaining_time":3.649343486},
{"learn":[35.8821774],"iteration":111,"passed_time":0.4579711784,"remaining_time":3.6310572},
{"learn":[35.85697209],"iteration":112,"passed_time":0.4607001527,"remaining_time":3.616292349},
{"learn":[35.80307201],"iteration":113,"passed_time":0.4632902704,"remaining_time":3.60065947},
{"learn":[35.73241246],"iteration":114,"passed_time":0.4659200246,"remaining_time":3.58555845},
{"learn":[35.66596757],"iteration":115,"passed_time":0.4681905414,"remaining_time":3.567934815},
{"learn":[35.57370603],"iteration":116,"passed_time":0.4706879008,"remaining_time":3.55228561},
{"learn":[35.49694451],"iteration":117,"passed_time":0.4729540769,"remaining_time":3.53513132},
{"learn":[35.45051006],"iteration":118,"passed_time":0.475695362,"remaining_time":3.521744655},
{"learn":[35.41525969],"iteration":119,"passed_time":0.4782034052,"remaining_time":3.506824971},
{"learn":[35.34561566],"iteration":120,"passed_time":0.4808548471,"remaining_time":3.493152154},
{"learn":[35.31290072],"iteration":121,"passed_time":0.4828623439,"remaining_time":3.475025721},
{"learn":[35.26071538],"iteration":122,"passed_time":0.4848944343,"remaining_time":3.457336739},
{"learn":[35.19601335],"iteration":123,"passed_time":0.4868265455,"remaining_time":3.439193983},
{"learn":[35.13006281],"iteration":124,"passed_time":0.4892108245,"remaining_time":3.424475772},
{"learn":[35.08707474],"iteration":125,"passed_time":0.4912447984,"remaining_time":3.407523443},
{"learn":[35.04522187],"iteration":126,"passed_time":0.4932951496,"remaining_time":3.390918627},
{"learn":[35.00474547],"iteration":127,"passed_time":0.4957691578,"remaining_time":3.377427388},
{"learn":[34.9456027],"iteration":128,"passed_time":0.4980750365,"remaining_time":3.362971758},
{"learn":[34.91344746],"iteration":129,"passed_time":0.5004952541,"remaining_time":3.349468239},
{"learn":[34.86995755],"iteration":130,"passed_time":0.5028246413,"remaining_time":3.335531399},
{"learn":[34.81139223],"iteration":131,"passed_time":0.5054983181,"remaining_time":3.324034395},
{"learn":[34.78284818],"iteration":132,"passed_time":0.5075554721,"remaining_time":3.308651085},
{"learn":[34.74453395],"iteration":133,"passed_time":0.5101950649,"remaining_time":3.297230793},
{"learn":[34.70681534],"iteration":134,"passed_time":0.5127784874,"remaining_time":3.285580678},
{"learn":[34.66898777],"iteration":135,"passed_time":0.5155575424,"remaining_time":3.27530674},
{"learn":[34.61539051],"iteration":136,"passed_time":0.5182793393,"remaining_time":3.264781532},
{"learn":[34.54840355],"iteration":137,"passed_time":0.5209239466,"remaining_time":3.253887261},
{"learn":[34.47380013],"iteration":138,"passed_time":0.5235156836,"remaining_time":3.242784199},
{"learn":[34.42613376],"iteration":139,"passed_time":0.5258547107,"remaining_time":3.230250366},
{"learn":[34.37347578],"iteration":140,"passed_time":0.528156067,"remaining_time":3.217631642},
{"learn":[34.33611202],"iteration":141,"passed_time":0.5306161127,"remaining_time":3.206117076},
{"learn":[34.29510544],"iteration":142,"passed_time":0.5326058639,"remaining_time":3.191910667},
{"learn":[34.24011291],"iteration":143,"passed_time":0.5345681746,"remaining_time":3.177710816},
{"learn":[34.18462039],"iteration":144,"passed_time":0.5368603828,"remaining_time":3.165625016},
{"learn":[34.13596686],"iteration":145,"passed_time":0.5393557367,"remaining_time":3.154861638},
{"learn":[34.10617497],"iteration":146,"passed_time":0.5416590022,"remaining_time":3.143096115},
{"learn":[34.05385526],"iteration":147,"passed_time":0.5438065195,"remaining_time":3.130561856},
{"learn":[34.0224134],"iteration":148,"passed_time":0.5458287021,"remaining_time":3.117451178},
{"learn":[33.99154516],"iteration":149,"passed_time":0.5480779769,"remaining_time":3.105775202},
{"learn":[33.94689757],"iteration":150,"passed_time":0.550123102,"remaining_time":3.093076249},
{"learn":[33.9055815],"iteration":151,"passed_time":0.5520052858,"remaining_time":3.079608437},
{"learn":[33.86340623],"iteration":152,"passed_time":0.5541958799,"remaining_time":3.067999414},
{"learn":[33.82678354],"iteration":153,"passed_time":0.5563453379,"remaining_time":3.056286726},
{"learn":[33.77887545],"iteration":154,"passed_time":0.5588827453,"remaining_time":3.046812386},
{"learn":[33.73091589],"iteration":155,"passed_time":0.5610018141,"remaining_time":3.035163661},
{"learn":[33.70805223],"iteration":156,"passed_time":0.5630995172,"remaining_time":3.023521612},
{"learn":[33.66011082],"iteration":157,"passed_time":0.5651599141,"remaining_time":3.011801567},
{"learn":[33.58585927],"iteration":158,"passed_time":0.5671958136,"remaining_time":3.000073454},
{"learn":[33.55194002],"iteration":159,"passed_time":0.5692605792,"remaining_time":2.988618041},
{"learn":[33.51823683],"iteration":160,"passed_time":0.5716212847,"remaining_time":2.978821477},
{"learn":[33.48124232],"iteration":161,"passed_time":0.5737228992,"remaining_time":2.967776478},
{"learn":[33.43508782],"iteration":162,"passed_time":0.5756020502,"remaining_time":2.955698871},
{"learn":[33.38844861],"iteration":163,"passed_time":0.5777182804,"remaining_time":2.944954161},
{"learn":[33.31293671],"iteration":164,"passed_time":0.5797008409,"remaining_time":2.933637589},
{"learn":[33.26678757],"iteration":165,"passed_time":0.5816126602,"remaining_time":2.922078064},
{"learn":[33.2127852],"iteration":166,"passed_time":0.5840345822,"remaining_time":2.913178485},
{"learn":[33.16110359],"iteration":167,"passed_time":0.5865634793,"remaining_time":2.904885802},
{"learn":[33.10049395],"iteration":168,"passed_time":0.5887473019,"remaining_time":2.894964544},
{"learn":[33.04163618],"iteration":169,"passed_time":0.5907763084,"remaining_time":2.884378447},
{"learn":[32.99323416],"iteration":170,"passed_time":0.5927380949,"remaining_time":2.873566554},
{"learn":[32.96257563],"iteration":171,"passed_time":0.5949652215,"remaining_time":2.864134904},
{"learn":[32.92184664],"iteration":172,"passed_time":0.5967060342,"remaining_time":2.852461793},
{"learn":[32.90800857],"iteration":173,"passed_time":0.5993417453,"remaining_time":2.845151044},
{"learn":[32.85150107],"iteration":174,"passed_time":0.6018334461,"remaining_time":2.837214817},
{"learn":[32.79125937],"iteration":175,"passed_time":0.6040538366,"remaining_time":2.828070235},
{"learn":[32.76299032],"iteration":176,"passed_time":0.6062279172,"remaining_time":2.818788564},
{"learn":[32.73230944],"iteration":177,"passed_time":0.6084116286,"remaining_time":2.809631229},
{"learn":[32.68981584],"iteration":178,"passed_time":0.6102869294,"remaining_time":2.799137257},
{"learn":[32.66606842],"iteration":179,"passed_time":0.6121830524,"remaining_time":2.788833905},
{"learn":[32.61624641],"iteration":180,"passed_time":0.614180597,"remaining_time":2.77908237},
{"learn":[32.57908111],"iteration":181,"passed_time":0.6164220993,"remaining_time":2.770512512},
{"learn":[32.5299876],"iteration":182,"passed_time":0.6189471154,"remaining_time":2.763277559},
{"learn":[32.5012083],"iteration":183,"passed_time":0.6208853113,"remaining_time":2.75349138},
{"learn":[32.44770221],"iteration":184,"passed_time":0.6229731704,"remaining_time":2.744449372},
{"learn":[32.40847803],"iteration":185,"passed_time":0.6248873209,"remaining_time":2.734721931},
{"learn":[32.34990585],"iteration":186,"passed_time":0.6268506077,"remaining_time":2.72529168},
{"learn":[32.28981575],"iteration":187,"passed_time":0.6286997615,"remaining_time":2.715447906},
{"learn":[32.22718965],"iteration":188,"passed_time":0.6309224238,"remaining_time":2.707291459},
{"learn":[32.19258721],"iteration":189,"passed_time":0.6331726707,"remaining_time":2.69931507},
{"learn":[32.13264128],"iteration":190,"passed_time":0.6351504325,"remaining_time":2.690244502},
{"learn":[32.09836012],"iteration":191,"passed_time":0.6373393195,"remaining_time":2.682136303},
{"learn":[32.06493035],"iteration":192,"passed_time":0.6392819803,"remaining_time":2.673059886},
{"learn":[32.02931777],"iteration":193,"passed_time":0.6411260627,"remaining_time":2.663647456},
{"learn":[31.97121204],"iteration":194,"passed_time":0.642993244,"remaining_time":2.654408007},
{"learn":[31.93852703],"iteration":195,"passed_time":0.6450871888,"remaining_time":2.646173978},
{"learn":[31.88426227],"iteration":196,"passed_time":0.6471214667,"remaining_time":2.637759075},
{"learn":[31.8387098],"iteration":197,"passed_time":0.6491899042,"remaining_time":2.629546986},
{"learn":[31.77480775],"iteration":198,"passed_time":0.6515438341,"remaining_time":2.622545785},
{"learn":[31.72375603],"iteration":199,"passed_time":0.653528935,"remaining_time":2.61411574},
{"learn":[31.66737992],"iteration":200,"passed_time":0.6556667834,"remaining_time":2.606357014},
{"learn":[31.58074175],"iteration":201,"passed_time":0.6576357295,"remaining_time":2.597986694},
{"learn":[31.54744189],"iteration":202,"passed_time":0.6596516631,"remaining_time":2.589863919},
{"learn":[31.50687577],"iteration":203,"passed_time":0.6617972671,"remaining_time":2.582306984},
{"learn":[31.453245],"iteration":204,"passed_time":0.6639269029,"remaining_time":2.574740916},
{"learn":[31.41129166],"iteration":205,"passed_time":0.666037003,"remaining_time":2.567152332},
{"learn":[31.35886168],"iteration":206,"passed_time":0.668022782,"remaining_time":2.559140416},
{"learn":[31.30911894],"iteration":207,"passed_time":0.6699845013,"remaining_time":2.551094832},
{"learn":[31.27185254],"iteration":208,"passed_time":0.6718481164,"remaining_time":2.542736172},
{"learn":[31.23682178],"iteration":209,"passed_time":0.6737762531,"remaining_time":2.534682095},
{"learn":[31.19415525],"iteration":210,"passed_time":0.6758486273,"remaining_time":2.527225436},
{"learn":[31.150393],"iteration":211,"passed_time":0.6778548436,"remaining_time":2.519573664},
{"learn":[31.11538149],"iteration":212,"passed_time":0.6798780231,"remaining_time":2.512037578},
{"learn":[31.08928004],"iteration":213,"passed_time":0.6820130068,"remaining_time":2.50496366},
{"learn":[31.02568982],"iteration":214,"passed_time":0.684197106,"remaining_time":2.498115015},
{"learn":[30.99037581],"iteration":215,"passed_time":0.6861812621,"remaining_time":2.49058384},
{"learn":[30.94594064],"iteration":216,"passed_time":0.6881065241,"remaining_time":2.482891283},
{"learn":[30.91900913],"iteration":217,"passed_time":0.6900734022,"remaining_time":2.47540092},
{"learn":[30.88112111],"iteration":218,"passed_time":0.6921909009,"remaining_time":2.468498144},
{"learn":[30.85440264],"iteration":219,"passed_time":0.6945276074,"remaining_time":2.462416063},
{"learn":[30.83510261],"iteration":220,"passed_time":0.6967832423,"remaining_time":2.456082107},
{"learn":[30.81142355],"iteration":221,"passed_time":0.6986803297,"remaining_time":2.448528363},
{"learn":[30.76211595],"iteration":222,"passed_time":0.7007002843,"remaining_time":2.441453457},
{"learn":[30.73783228],"iteration":223,"passed_time":0.7024082113,"remaining_time":2.433342732},
{"learn":[30.69744342],"iteration":224,"passed_time":0.7042069245,"remaining_time":2.425601629},
{"learn":[30.6466595],"iteration":225,"passed_time":0.7063194133,"remaining_time":2.418987725},
{"learn":[30.61567691],"iteration":226,"passed_time":0.7083363749,"remaining_time":2.412088184},
{"learn":[30.58166204],"iteration":227,"passed_time":0.7103630511,"remaining_time":2.405264366},
{"learn":[30.55021198],"iteration":228,"passed_time":0.7125303563,"remaining_time":2.398955916},
{"learn":[30.50780764],"iteration":229,"passed_time":0.7143856888,"remaining_time":2.391639045},
{"learn":[30.44965056],"iteration":230,"passed_time":0.716386319,"remaining_time":2.384853157},
{"learn":[30.43345121],"iteration":231,"passed_time":0.7187332109,"remaining_time":2.379254767},
{"learn":[30.35421962],"iteration":232,"passed_time":0.7210384502,"remaining_time":2.373547173},
{"learn":[30.30267505],"iteration":233,"passed_time":0.7231318758,"remaining_time":2.367175286},
{"learn":[30.2553747],"iteration":234,"passed_time":0.7251894453,"remaining_time":2.360723088},
{"learn":[30.185821],"iteration":235,"passed_time":0.7273666034,"remaining_time":2.354695276},
{"learn":[30.13518212],"iteration":236,"passed_time":0.7296360382,"remaining_time":2.348997034},
{"learn":[30.0833974],"iteration":237,"passed_time":0.7318037899,"remaining_time":2.34300205},
{"learn":[30.03129573],"iteration":238,"passed_time":0.7337952543,"remaining_time":2.336477776},
{"learn":[29.98246415],"iteration":239,"passed_time":0.7359937972,"remaining_time":2.330647024},
{"learn":[29.93298927],"iteration":240,"passed_time":0.7378442074,"remaining_time":2.323750014},
{"learn":[29.91326852],"iteration":241,"passed_time":0.7396467732,"remaining_time":2.316744852},
{"learn":[29.86899574],"iteration":242,"passed_time":0.7419737233,"remaining_time":2.311416084},
{"learn":[29.84427405],"iteration":243,"passed_time":0.7440436895,"remaining_time":2.305315694},
{"learn":[29.82003551],"iteration":244,"passed_time":0.7458861092,"remaining_time":2.29854699},
{"learn":[29.79553279],"iteration":245,"passed_time":0.7480711713,"remaining_time":2.29286855},
{"learn":[29.76759392],"iteration":246,"passed_time":0.7503801744,"remaining_time":2.28759624},
{"learn":[29.72561637],"iteration":247,"passed_time":0.7521732767,"remaining_time":2.280783484},
{"learn":[29.68678377],"iteration":248,"passed_time":0.7543832153,"remaining_time":2.275268252},
{"learn":[29.6260023],"iteration":249,"passed_time":0.7563903947,"remaining_time":2.269171184},
{"learn":[29.56778345],"iteration":250,"passed_time":0.7585411038,"remaining_time":2.263535007},
{"learn":[29.52031441],"iteration":251,"passed_time":0.7606367647,"remaining_time":2.257763095},
{"learn":[29.44590814],"iteration":252,"passed_time":0.762586661,"remaining_time":2.251589865},
{"learn":[29.39584686],"iteration":253,"passed_time":0.7646376977,"remaining_time":2.245746939},
{"learn":[29.36721172],"iteration":254,"passed_time":0.7664156342,"remaining_time":2.239135872},
{"learn":[29.31490833],"iteration":255,"passed_time":0.7682646763,"remaining_time":2.232769216},
{"learn":[29.26329528],"iteration":256,"passed_time":0.7703953942,"remaining_time":2.227252054},
{"learn":[29.1949613],"iteration":257,"passed_time":0.7723185832,"remaining_time":2.221164297},
{"learn":[29.15525278],"iteration":258,"passed_time":0.7744571966,"remaining_time":2.21572503},
{"learn":[29.09976305],"iteration":259,"passed_time":0.7766376805,"remaining_time":2.210430321},
{"learn":[29.04660436],"iteration":260,"passed_time":0.7788553122,"remaining_time":2.205264658},
{"learn":[28.99011722],"iteration":261,"passed_time":0.7809958563,"remaining_time":2.199904359},
{"learn":[28.93904322],"iteration":262,"passed_time":0.7830192493,"remaining_time":2.194240254},
{"learn":[28.89233098],"iteration":263,"passed_time":0.785240888,"remaining_time":2.189156415},
{"learn":[28.85594682],"iteration":264,"passed_time":0.7873781985,"remaining_time":2.183860286},
{"learn":[28.81885106],"iteration":265,"passed_time":0.7894767876,"remaining_time":2.17848106},
{"learn":[28.74921001],"iteration":266,"passed_time":0.7921076833,"remaining_time":2.17458776},
{"learn":[28.71410627],"iteration":267,"passed_time":0.794305873,"remaining_time":2.169522011},
{"learn":[28.65263882],"iteration":268,"passed_time":0.7966112857,"remaining_time":2.164768959},
{"learn":[28.62244788],"iteration":269,"passed_time":0.799118918,"remaining_time":2.160580778},
{"learn":[28.55851244],"iteration":270,"passed_time":0.8013537689,"remaining_time":2.155671209},
{"learn":[28.53066425],"iteration":271,"passed_time":0.8034362811,"remaining_time":2.150373576},
{"learn":[28.46512015],"iteration":272,"passed_time":0.8057228407,"remaining_time":2.145642876},
{"learn":[28.42944048],"iteration":273,"passed_time":0.8078074663,"remaining_time":2.140394966},
{"learn":[28.37703906],"iteration":274,"passed_time":0.8102384309,"remaining_time":2.136083136},
{"learn":[28.34736978],"iteration":275,"passed_time":0.8122437461,"remaining_time":2.130668378},
{"learn":[28.29706497],"iteration":276,"passed_time":0.814133703,"remaining_time":2.124977138},
{"learn":[28.26316987],"iteration":277,"passed_time":0.8161536963,"remaining_time":2.119650967},
{"learn":[28.23768972],"iteration":278,"passed_time":0.8180984157,"remaining_time":2.11415397},
{"learn":[28.20346355],"iteration":279,"passed_time":0.8203356559,"remaining_time":2.109434544},
{"learn":[28.17492434],"iteration":280,"passed_time":0.8226459926,"remaining_time":2.104919817},
{"learn":[28.12298502],"iteration":281,"passed_time":0.8252969875,"remaining_time":2.101288075},
{"learn":[28.09955063],"iteration":282,"passed_time":0.8275532184,"remaining_time":2.096663101},
{"learn":[28.06765058],"iteration":283,"passed_time":0.829709366,"remaining_time":2.091802486},
{"learn":[28.04288932],"iteration":284,"passed_time":0.8315982698,"remaining_time":2.086290396},
{"learn":[28.01815632],"iteration":285,"passed_time":0.8334816904,"remaining_time":2.080789954},
{"learn":[27.96328541],"iteration":286,"passed_time":0.835602928,"remaining_time":2.075905532},
{"learn":[27.9501706],"iteration":287,"passed_time":0.8380926179,"remaining_time":2.071951194},
{"learn":[27.91861377],"iteration":288,"passed_time":0.8405124667,"remaining_time":2.067835169},
{"learn":[27.9030494],"iteration":289,"passed_time":0.8427284548,"remaining_time":2.063231734},
{"learn":[27.87269851],"iteration":290,"passed_time":0.8447771576,"remaining_time":2.05823713},
{"learn":[27.83197152],"iteration":291,"passed_time":0.8467376882,"remaining_time":2.053048915},
{"learn":[27.82252159],"iteration":292,"passed_time":0.8487187945,"remaining_time":2.047932381},
{"learn":[27.78066958],"iteration":293,"passed_time":0.850706878,"remaining_time":2.042853931},
{"learn":[27.76831476],"iteration":294,"passed_time":0.8532079683,"remaining_time":2.039022433},
{"learn":[27.7456883],"iteration":295,"passed_time":0.8551365768,"remaining_time":2.033838345},
{"learn":[27.72035392],"iteration":296,"passed_time":0.8571425148,"remaining_time":2.028859218},
{"learn":[27.6997237],"iteration":297,"passed_time":0.8590002186,"remaining_time":2.023550851},
{"learn":[27.64824791],"iteration":298,"passed_time":0.8609717572,"remaining_time":2.018532447},
{"learn":[27.63288354],"iteration":299,"passed_time":0.863015846,"remaining_time":2.013703641},
{"learn":[27.60217035],"iteration":300,"passed_time":0.8650427164,"remaining_time":2.008853351},
{"learn":[27.58434502],"iteration":301,"passed_time":0.8671802096,"remaining_time":2.004277438},
{"learn":[27.56465598],"iteration":302,"passed_time":0.8698626648,"remaining_time":2.000971212},
{"learn":[27.52011379],"iteration":303,"passed_time":0.8722590755,"remaining_time":1.997014199},
{"learn":[27.50023212],"iteration":304,"passed_time":0.8742339512,"remaining_time":1.992106872},
{"learn":[27.47268454],"iteration":305,"passed_time":0.876209166,"remaining_time":1.987219481},
{"learn":[27.4160086],"iteration":306,"passed_time":0.8780911964,"remaining_time":1.982140714},
{"learn":[27.40232492],"iteration":307,"passed_time":0.8801770361,"remaining_time":1.977540614},
{"learn":[27.34827813],"iteration":308,"passed_time":0.8824943209,"remaining_time":1.973474355},
{"learn":[27.30631517],"iteration":309,"passed_time":0.8850481928,"remaining_time":1.969945977},
{"learn":[27.26899307],"iteration":310,"passed_time":0.8870403437,"remaining_time":1.965179411},
{"learn":[27.22254534],"iteration":311,"passed_time":0.8888394073,"remaining_time":1.960004847},
{"learn":[27.19326225],"iteration":312,"passed_time":0.8906944957,"remaining_time":1.95497482},
{"learn":[27.15553619],"iteration":313,"passed_time":0.8925635719,"remaining_time":1.949995574},
{"learn":[27.13799757],"iteration":314,"passed_time":0.8945998266,"remaining_time":1.945399623},
{"learn":[27.11126654],"iteration":315,"passed_time":0.8963909438,"remaining_time":1.940289258},
{"learn":[27.08918586],"iteration":316,"passed_time":0.8984442903,"remaining_time":1.935764827},
{"learn":[27.04096932],"iteration":317,"passed_time":0.9005108456,"remaining_time":1.931284266},
{"learn":[27.03804477],"iteration":318,"passed_time":0.9026345771,"remaining_time":1.9269409},
{"learn":[26.99033212],"iteration":319,"passed_time":0.9047409533,"remaining_time":1.922574526},
{"learn":[26.93753101],"iteration":320,"passed_time":0.9065611163,"remaining_time":1.917616816},
{"learn":[26.89149658],"iteration":321,"passed_time":0.9086452435,"remaining_time":1.913234395},
{"learn":[26.83995568],"iteration":322,"passed_time":0.9106051428,"remaining_time":1.908605826},
{"learn":[26.80254351],"iteration":323,"passed_time":0.9128089854,"remaining_time":1.904502698},
{"learn":[26.73427507],"iteration":324,"passed_time":0.9154673712,"remaining_time":1.901355309},
{"learn":[26.68923654],"iteration":325,"passed_time":0.9179947345,"remaining_time":1.897940034},
{"learn":[26.65314012],"iteration":326,"passed_time":0.9202769213,"remaining_time":1.89402559},
{"learn":[26.63362783],"iteration":327,"passed_time":0.9221117471,"remaining_time":1.889204555},
{"learn":[26.60499833],"iteration":328,"passed_time":0.9239331339,"remaining_time":1.884374264},
{"learn":[26.556579],"iteration":329,"passed_time":0.9261567491,"remaining_time":1.880378854},
{"learn":[26.51751662],"iteration":330,"passed_time":0.9281549161,"remaining_time":1.875938486},
{"learn":[26.47709464],"iteration":331,"passed_time":0.9303420668,"remaining_time":1.871893074},
{"learn":[26.44326271],"iteration":332,"passed_time":0.932705505,"remaining_time":1.868211927},
{"learn":[26.40229003],"iteration":333,"passed_time":0.9346547976,"remaining_time":1.86371286},
{"learn":[26.3580957],"iteration":334,"passed_time":0.936663753,"remaining_time":1.85934745},
{"learn":[26.33077171],"iteration":335,"passed_time":0.9386271925,"remaining_time":1.854906118},
{"learn":[26.30216752],"iteration":336,"passed_time":0.9405814521,"remaining_time":1.850461433},
{"learn":[26.27533968],"iteration":337,"passed_time":0.9423528784,"remaining_time":1.845673389},
{"learn":[26.22319113],"iteration":338,"passed_time":0.9442626278,"remaining_time":1.841172852},
{"learn":[26.2003135],"iteration":339,"passed_time":0.9464219397,"remaining_time":1.837172001},
{"learn":[26.15765871],"iteration":340,"passed_time":0.9485703778,"remaining_time":1.833160935},
{"learn":[26.11840064],"iteration":341,"passed_time":0.9504817263,"remaining_time":1.828704608},
{"learn":[26.06124906],"iteration":342,"passed_time":0.9528903657,"remaining_time":1.825215657},
{"learn":[26.03153894],"iteration":343,"passed_time":0.9549108786,"remaining_time":1.820992838},
{"learn":[25.966092],"iteration":344,"passed_time":0.9569373714,"remaining_time":1.81679414},
{"learn":[25.93332929],"iteration":345,"passed_time":0.9587001531,"remaining_time":1.812109538},
{"learn":[25.88999694],"iteration":346,"passed_time":0.9605247304,"remaining_time":1.807558066},
{"learn":[25.83660321],"iteration":347,"passed_time":0.9626747235,"remaining_time":1.803631953},
{"learn":[25.78927005],"iteration":348,"passed_time":0.9646910621,"remaining_time":1.799466709},
{"learn":[25.77667074],"iteration":349,"passed_time":0.9664985302,"remaining_time":1.794925842},
{"learn":[25.74889117],"iteration":350,"passed_time":0.9683528695,"remaining_time":1.790487215},
{"learn":[25.70097306],"iteration":351,"passed_time":0.970216388,"remaining_time":1.786080169},
{"learn":[25.67563145],"iteration":352,"passed_time":0.9722218503,"remaining_time":1.781947697},
{"learn":[25.63994079],"iteration":353,"passed_time":0.9741083424,"remaining_time":1.777610139},
{"learn":[25.60119819],"iteration":354,"passed_time":0.9760793157,"remaining_time":1.773439883},
{"learn":[25.57476415],"iteration":355,"passed_time":0.9779182951,"remaining_time":1.769043208},
{"learn":[25.5442692],"iteration":356,"passed_time":0.9798106827,"remaining_time":1.764757056},
{"learn":[25.49390412],"iteration":357,"passed_time":0.9817810536,"remaining_time":1.760624124},
{"learn":[25.45598607],"iteration":358,"passed_time":0.9835770688,"remaining_time":1.756191925},
{"learn":[25.42085546],"iteration":359,"passed_time":0.9854681027,"remaining_time":1.751943294},
{"learn":[25.38496644],"iteration":360,"passed_time":0.9874673317,"remaining_time":1.747899238},
{"learn":[25.37859287],"iteration":361,"passed_time":0.9893458524,"remaining_time":1.74365374},
{"learn":[25.34551892],"iteration":362,"passed_time":0.991278595,"remaining_time":1.739516433},
{"learn":[25.33662503],"iteration":363,"passed_time":0.9930890007,"remaining_time":1.735177485},
{"learn":[25.28162421],"iteration":364,"passed_time":0.9952565991,"remaining_time":1.731473809},
{"learn":[25.2267903],"iteration":365,"passed_time":0.9976453772,"remaining_time":1.728161664},
{"learn":[25.19113332],"iteration":366,"passed_time":0.9999357302,"remaining_time":1.724684788},
{"learn":[25.16732919],"iteration":367,"passed_time":1.002135927,"remaining_time":1.721059526},
{"learn":[25.11788315],"iteration":368,"passed_time":1.004267848,"remaining_time":1.717325236},
{"learn":[25.08251995],"iteration":369,"passed_time":1.006045452,"remaining_time":1.712996311},
{"learn":[25.04959958],"iteration":370,"passed_time":1.007877231,"remaining_time":1.708772987},
{"learn":[25.01675416],"iteration":371,"passed_time":1.009765023,"remaining_time":1.704657082},
{"learn":[24.96564954],"iteration":372,"passed_time":1.011903152,"remaining_time":1.700973931},
{"learn":[24.92361046],"iteration":373,"passed_time":1.014010554,"remaining_time":1.697247611},
{"learn":[24.88743827],"iteration":374,"passed_time":1.016446755,"remaining_time":1.694077924},
{"learn":[24.85937312],"iteration":375,"passed_time":1.018961334,"remaining_time":1.691042214},
{"learn":[24.81548005],"iteration":376,"passed_time":1.021152,"remaining_time":1.687473994},
{"learn":[24.780721],"iteration":377,"passed_time":1.023307529,"remaining_time":1.683855246},
{"learn":[24.75804526],"iteration":378,"passed_time":1.02588675,"remaining_time":1.680938447},
{"learn":[24.73472519],"iteration":379,"passed_time":1.028458418,"remaining_time":1.678011103},
{"learn":[24.72021424],"iteration":380,"passed_time":1.030529256,"remaining_time":1.674271941},
{"learn":[24.67948805],"iteration":381,"passed_time":1.032908453,"remaining_time":1.671040376},
{"learn":[24.64396988],"iteration":382,"passed_time":1.034816459,"remaining_time":1.667054191},
{"learn":[24.60757119],"iteration":383,"passed_time":1.036763567,"remaining_time":1.663141555},
{"learn":[24.58588334],"iteration":384,"passed_time":1.039086515,"remaining_time":1.659839499},
{"learn":[24.54562545],"iteration":385,"passed_time":1.041595826,"remaining_time":1.656838957},
{"learn":[24.52168392],"iteration":386,"passed_time":1.044681571,"remaining_time":1.654754013},
{"learn":[24.48281445],"iteration":387,"passed_time":1.047049034,"remaining_time":1.651530951},
{"learn":[24.45502216],"iteration":388,"passed_time":1.04954829,"remaining_time":1.648519294},
{"learn":[24.4158903],"iteration":389,"passed_time":1.051483506,"remaining_time":1.644628047},
{"learn":[24.37398399],"iteration":390,"passed_time":1.05361705,"remaining_time":1.641055712},
{"learn":[24.34119039],"iteration":391,"passed_time":1.055649179,"remaining_time":1.637333421},
{"learn":[24.33231215],"iteration":392,"passed_time":1.057556048,"remaining_time":1.633426262},
{"learn":[24.27153045],"iteration":393,"passed_time":1.059363096,"remaining_time":1.629375727},
{"learn":[24.25218823],"iteration":394,"passed_time":1.06149746,"remaining_time":1.625837881},
{"learn":[24.22062618],"iteration":395,"passed_time":1.063444104,"remaining_time":1.622020806},
{"learn":[24.18455429],"iteration":396,"passed_time":1.065577876,"remaining_time":1.618497378},
{"learn":[24.15630849],"iteration":397,"passed_time":1.067498123,"remaining_time":1.614657966},
{"learn":[24.11205923],"iteration":398,"passed_time":1.06924648,"remaining_time":1.610569259},
{"learn":[24.08897634],"iteration":399,"passed_time":1.071096119,"remaining_time":1.606644179},
{"learn":[24.05967554],"iteration":400,"passed_time":1.073154547,"remaining_time":1.60304133},
{"learn":[24.00081607],"iteration":401,"passed_time":1.07540101,"remaining_time":1.599725881},
{"learn":[23.97524118],"iteration":402,"passed_time":1.077571452,"remaining_time":1.596303118},
{"learn":[23.94396236],"iteration":403,"passed_time":1.079539898,"remaining_time":1.592588562},
{"learn":[23.90118465],"iteration":404,"passed_time":1.081543526,"remaining_time":1.588934316},
{"learn":[23.86539301],"iteration":405,"passed_time":1.083235389,"remaining_time":1.584832072},
{"learn":[23.82476262],"iteration":406,"passed_time":1.084952836,"remaining_time":1.580778947},
{"learn":[23.78875521],"iteration":407,"passed_time":1.086879107,"remaining_time":1.577040273},
{"learn":[23.7753763],"iteration":408,"passed_time":1.089137297,"remaining_time":1.57379008},
{"learn":[23.74820453],"iteration":409,"passed_time":1.091093093,"remaining_time":1.570109572},
{"learn":[23.70384653],"iteration":410,"passed_time":1.093361286,"remaining_time":1.566885152},
{"learn":[23.66413609],"iteration":411,"passed_time":1.095312343,"remaining_time":1.563212761},
{"learn":[23.64968124],"iteration":412,"passed_time":1.097259253,"remaining_time":1.559542813},
{"learn":[23.6372431],"iteration":413,"passed_time":1.099127963,"remaining_time":1.555770498},
{"learn":[23.63537259],"iteration":414,"passed_time":1.100958917,"remaining_time":1.551954136},
{"learn":[23.6125204],"iteration":415,"passed_time":1.102839691,"remaining_time":1.548217258},
{"learn":[23.57564676],"iteration":416,"passed_time":1.105213725,"remaining_time":1.5451789},
{"learn":[23.5554567],"iteration":417,"passed_time":1.10753628,"remaining_time":1.542072045},
{"learn":[23.51623384],"iteration":418,"passed_time":1.109412115,"remaining_time":1.538349496},
{"learn":[23.46717036],"iteration":419,"passed_time":1.111085992,"remaining_time":1.534356846},
{"learn":[23.43151935],"iteration":420,"passed_time":1.112911955,"remaining_time":1.530584375},
{"learn":[23.39795883],"iteration":421,"passed_time":1.114707504,"remaining_time":1.526779473},
{"learn":[23.36983249],"iteration":422,"passed_time":1.116582835,"remaining_time":1.523092897},
{"learn":[23.33768293],"iteration":423,"passed_time":1.118830735,"remaining_time":1.519920999},
{"learn":[23.30395294],"iteration":424,"passed_time":1.121161427,"remaining_time":1.51686546},
{"learn":[23.27274695],"iteration":425,"passed_time":1.123210745,"remaining_time":1.513434197},
{"learn":[23.26479785],"iteration":426,"passed_time":1.1252318,"remaining_time":1.509971479},
{"learn":[23.20884448],"iteration":427,"passed_time":1.127256553,"remaining_time":1.506520439},
{"learn":[23.1814546],"iteration":428,"passed_time":1.129128068,"remaining_time":1.502872091},
{"learn":[23.14422699],"iteration":429,"passed_time":1.130960166,"remaining_time":1.499179755},
{"learn":[23.12569135],"iteration":430,"passed_time":1.132888022,"remaining_time":1.49562247},
{"learn":[23.11328766],"iteration":431,"passed_time":1.135239338,"remaining_time":1.4926295},
{"learn":[23.09936361],"iteration":432,"passed_time":1.137294325,"remaining_time":1.489251461},
{"learn":[23.06531839],"iteration":433,"passed_time":1.139224305,"remaining_time":1.48571649},
{"learn":[23.03071813],"iteration":434,"passed_time":1.141058887,"remaining_time":1.482064991},
{"learn":[23.00547773],"iteration":435,"passed_time":1.143168631,"remaining_time":1.47877777},
{"learn":[22.98102601],"iteration":436,"passed_time":1.145201277,"remaining_time":1.47539661},
{"learn":[22.97154607],"iteration":437,"passed_time":1.146845281,"remaining_time":1.47152294},
{"learn":[22.92501612],"iteration":438,"passed_time":1.148617548,"remaining_time":1.467823336},
{"learn":[22.87282235],"iteration":439,"passed_time":1.150243219,"remaining_time":1.463945916},
{"learn":[22.84637925],"iteration":440,"passed_time":1.152404292,"remaining_time":1.460757368},
{"learn":[22.8216421],"iteration":441,"passed_time":1.154135326,"remaining_time":1.45703057},
{"learn":[22.77759796],"iteration":442,"passed_time":1.155877224,"remaining_time":1.453326442},
{"learn":[22.75620423],"iteration":443,"passed_time":1.157756282,"remaining_time":1.449802912},
{"learn":[22.70134968],"iteration":444,"passed_time":1.159345246,"remaining_time":1.445924969},
{"learn":[22.65050144],"iteration":445,"passed_time":1.161149759,"remaining_time":1.442325037},
{"learn":[22.6237448],"iteration":446,"passed_time":1.162987365,"remaining_time":1.438774077},
{"learn":[22.61073403],"iteration":447,"passed_time":1.165262104,"remaining_time":1.435769378},
{"learn":[22.58335447],"iteration":448,"passed_time":1.167190683,"remaining_time":1.432343132},
{"learn":[22.55887233],"iteration":449,"passed_time":1.16934002,"remaining_time":1.429193358},
{"learn":[22.52914992],"iteration":450,"passed_time":1.171150217,"remaining_time":1.425635187},
{"learn":[22.49139482],"iteration":451,"passed_time":1.172989173,"remaining_time":1.422119617},
{"learn":[22.4696373],"iteration":452,"passed_time":1.174823998,"remaining_time":1.418606461},
{"learn":[22.42440835],"iteration":453,"passed_time":1.176769198,"remaining_time":1.415233441},
{"learn":[22.39891333],"iteration":454,"passed_time":1.178774531,"remaining_time":1.411938724},
{"learn":[22.37054262],"iteration":455,"passed_time":1.180535116,"remaining_time":1.408357682},
{"learn":[22.34303203],"iteration":456,"passed_time":1.182640736,"remaining_time":1.405194572},
{"learn":[22.3064931],"iteration":457,"passed_time":1.184903603,"remaining_time":1.402222167},
{"learn":[22.282291],"iteration":458,"passed_time":1.186905442,"remaining_time":1.398945194},
{"learn":[22.24938257],"iteration":459,"passed_time":1.188534871,"remaining_time":1.395236588},
{"learn":[22.21413621],"iteration":460,"passed_time":1.190281895,"remaining_time":1.391674494},
{"learn":[22.19959875],"iteration":461,"passed_time":1.192028289,"remaining_time":1.388119523},
{"learn":[22.15087619],"iteration":462,"passed_time":1.193667111,"remaining_time":1.384447599},
{"learn":[22.14079241],"iteration":463,"passed_time":1.1953704,"remaining_time":1.38085891},
{"learn":[22.12065602],"iteration":464,"passed_time":1.197029071,"remaining_time":1.377226996},
{"learn":[22.08559371],"iteration":465,"passed_time":1.198987136,"remaining_time":1.373946633},
{"learn":[22.07030012],"iteration":466,"passed_time":1.200987257,"remaining_time":1.370719932},
{"learn":[22.03142382],"iteration":467,"passed_time":1.202846368,"remaining_time":1.367338179},
{"learn":[22.01219506],"iteration":468,"passed_time":1.204595393,"remaining_time":1.36383828},
{"learn":[21.96395883],"iteration":469,"passed_time":1.2063145,"remaining_time":1.360312096},
{"learn":[21.95737309],"iteration":470,"passed_time":1.208134242,"remaining_time":1.356906611},
{"learn":[21.94671161],"iteration":471,"passed_time":1.209942656,"remaining_time":1.353495175},
{"learn":[21.93288872],"iteration":472,"passed_time":1.211877806,"remaining_time":1.350231721},
{"learn":[21.88983667],"iteration":473,"passed_time":1.213895722,"remaining_time":1.347065717},
{"learn":[21.87222788],"iteration":474,"passed_time":1.215835843,"remaining_time":1.343818564},
{"learn":[21.84783044],"iteration":475,"passed_time":1.21792194,"remaining_time":1.340737597},
{"learn":[21.82182184],"iteration":476,"passed_time":1.21966745,"remaining_time":1.337287372},
{"learn":[21.78480972],"iteration":477,"passed_time":1.221351996,"remaining_time":1.333777703},
{"learn":[21.74424552],"iteration":478,"passed_time":1.223216885,"remaining_time":1.33047181},
{"learn":[21.7175451],"iteration":479,"passed_time":1.225095522,"remaining_time":1.327186816},
{"learn":[21.68711308],"iteration":480,"passed_time":1.227057563,"remaining_time":1.323997661},
{"learn":[21.64303967],"iteration":481,"passed_time":1.228880235,"remaining_time":1.320663821},
{"learn":[21.61728763],"iteration":482,"passed_time":1.231015373,"remaining_time":1.317670699},
{"learn":[21.59858579],"iteration":483,"passed_time":1.233064235,"remaining_time":1.314589143},
{"learn":[21.56704563],"iteration":484,"passed_time":1.234978269,"remaining_time":1.311368677},
{"learn":[21.53852119],"iteration":485,"passed_time":1.237023007,"remaining_time":1.308291822},
{"learn":[21.4983644],"iteration":486,"passed_time":1.239124424,"remaining_time":1.30527891},
{"learn":[21.4687972],"iteration":487,"passed_time":1.241109996,"remaining_time":1.302148192},
{"learn":[21.44722416],"iteration":488,"passed_time":1.243006925,"remaining_time":1.298929527},
{"learn":[21.40776443],"iteration":489,"passed_time":1.24506106,"remaining_time":1.295879879},
{"learn":[21.37973303],"iteration":490,"passed_time":1.247243717,"remaining_time":1.292967519},
{"learn":[21.34132147],"iteration":491,"passed_time":1.249244398,"remaining_time":1.289870232},
{"learn":[21.30040788],"iteration":492,"passed_time":1.251291489,"remaining_time":1.286825121},
{"learn":[21.27214257],"iteration":493,"passed_time":1.253475795,"remaining_time":1.283924599},
{"learn":[21.23113417],"iteration":494,"passed_time":1.255680599,"remaining_time":1.281047883},
{"learn":[21.20859549],"iteration":495,"passed_time":1.25790842,"remaining_time":1.278197265},
{"learn":[21.17238438],"iteration":496,"passed_time":1.260185821,"remaining_time":1.275399332},
{"learn":[21.14616246],"iteration":497,"passed_time":1.262320947,"remaining_time":1.272460071},
{"learn":[21.12459974],"iteration":498,"passed_time":1.264595801,"remaining_time":1.269664321},
{"learn":[21.1036952],"iteration":499,"passed_time":1.266514673,"remaining_time":1.266514673},
{"learn":[21.06410873],"iteration":500,"passed_time":1.268398513,"remaining_time":1.263335045},
{"learn":[21.03098244],"iteration":501,"passed_time":1.269991745,"remaining_time":1.259872289},
{"learn":[20.99209133],"iteration":502,"passed_time":1.271726426,"remaining_time":1.256556727},
{"learn":[20.95137044],"iteration":503,"passed_time":1.273551658,"remaining_time":1.253336552},
{"learn":[20.91845037],"iteration":504,"passed_time":1.275230306,"remaining_time":1.249978221},
{"learn":[20.88860303],"iteration":505,"passed_time":1.276896848,"remaining_time":1.246614709},
{"learn":[20.86735712],"iteration":506,"passed_time":1.278814391,"remaining_time":1.243501962},
{"learn":[20.84426082],"iteration":507,"passed_time":1.280441577,"remaining_time":1.240112709},
{"learn":[20.81441088],"iteration":508,"passed_time":1.282139706,"remaining_time":1.236798813},
{"learn":[20.78266063],"iteration":509,"passed_time":1.283794791,"remaining_time":1.233449897},
{"learn":[20.74985967],"iteration":510,"passed_time":1.2854516,"remaining_time":1.230109261},
{"learn":[20.72293608],"iteration":511,"passed_time":1.28741761,"remaining_time":1.227069909},
{"learn":[20.69895983],"iteration":512,"passed_time":1.289290659,"remaining_time":1.223946493},
{"learn":[20.66768454],"iteration":513,"passed_time":1.290928396,"remaining_time":1.220605448},
{"learn":[20.64320182],"iteration":514,"passed_time":1.292973641,"remaining_time":1.217654788},
{"learn":[20.61289113],"iteration":515,"passed_time":1.294803006,"remaining_time":1.214505145},
{"learn":[20.58413142],"iteration":516,"passed_time":1.29672297,"remaining_time":1.211445251},
{"learn":[20.57039077],"iteration":517,"passed_time":1.298371725,"remaining_time":1.208137397},
{"learn":[20.54614577],"iteration":518,"passed_time":1.300369996,"remaining_time":1.205159861},
{"learn":[20.51422594],"iteration":519,"passed_time":1.301975278,"remaining_time":1.201823334},
{"learn":[20.47873152],"iteration":520,"passed_time":1.303891182,"remaining_time":1.198779033},
{"learn":[20.4459622],"iteration":521,"passed_time":1.305567472,"remaining_time":1.19551964},
{"learn":[20.4243324],"iteration":522,"passed_time":1.307421744,"remaining_time":1.192428627},
{"learn":[20.39385874],"iteration":523,"passed_time":1.309208203,"remaining_time":1.189280734},
{"learn":[20.35943492],"iteration":524,"passed_time":1.310785771,"remaining_time":1.18594903},
{"learn":[20.34227746],"iteration":525,"passed_time":1.312320058,"remaining_time":1.182584995},
{"learn":[20.30855908],"iteration":526,"passed_time":1.31434179,"remaining_time":1.179665402},
{"learn":[20.26337188],"iteration":527,"passed_time":1.316117817,"remaining_time":1.176529563},
{"learn":[20.2192197],"iteration":528,"passed_time":1.31783049,"remaining_time":1.173342459},
{"learn":[20.1935481],"iteration":529,"passed_time":1.319628433,"remaining_time":1.170236535},
{"learn":[20.16731782],"iteration":530,"passed_time":1.321499327,"remaining_time":1.167199971},
{"learn":[20.13428819],"iteration":531,"passed_time":1.323167454,"remaining_time":1.163989414},
{"learn":[20.11391205],"iteration":532,"passed_time":1.325004151,"remaining_time":1.160932342},
{"learn":[20.08571582],"iteration":533,"passed_time":1.326903361,"remaining_time":1.157934394},
{"learn":[20.06171492],"iteration":534,"passed_time":1.328594882,"remaining_time":1.154760038},
{"learn":[20.03983293],"iteration":535,"passed_time":1.330282085,"remaining_time":1.151587476},
{"learn":[20.01118583],"iteration":536,"passed_time":1.331853792,"remaining_time":1.148320867},
{"learn":[20.00120255],"iteration":537,"passed_time":1.333589105,"remaining_time":1.145201053},
{"learn":[19.96925614],"iteration":538,"passed_time":1.33543878,"remaining_time":1.142184188},
{"learn":[19.94803645],"iteration":539,"passed_time":1.337125523,"remaining_time":1.139032853},
{"learn":[19.92079296],"iteration":540,"passed_time":1.338643179,"remaining_time":1.135743474},
{"learn":[19.88641786],"iteration":541,"passed_time":1.340488962,"remaining_time":1.132737905},
{"learn":[19.86234126],"iteration":542,"passed_time":1.342278565,"remaining_time":1.129689326},
{"learn":[19.82822078],"iteration":543,"passed_time":1.344123602,"remaining_time":1.126691842},
{"learn":[19.8001402],"iteration":544,"passed_time":1.345950884,"remaining_time":1.123683765},
{"learn":[19.76382957],"iteration":545,"passed_time":1.347687143,"remaining_time":1.120604328},
{"learn":[19.744412],"iteration":546,"passed_time":1.349366854,"remaining_time":1.117482971},
{"learn":[19.7288241],"iteration":547,"passed_time":1.350963445,"remaining_time":1.114298316},
{"learn":[19.70022899],"iteration":548,"passed_time":1.352653766,"remaining_time":1.111196445},
{"learn":[19.68294028],"iteration":549,"passed_time":1.354277142,"remaining_time":1.108044934},
{"learn":[19.66326106],"iteration":550,"passed_time":1.356212893,"remaining_time":1.105153519},
{"learn":[19.65915723],"iteration":551,"passed_time":1.358044596,"remaining_time":1.102181121},
{"learn":[19.62252394],"iteration":552,"passed_time":1.360011776,"remaining_time":1.099322358},
{"learn":[19.60311777],"iteration":553,"passed_time":1.361678481,"remaining_time":1.096224914},
{"learn":[19.56577643],"iteration":554,"passed_time":1.363481587,"remaining_time":1.093241993},
{"learn":[19.564881],"iteration":555,"passed_time":1.365040055,"remaining_time":1.090067958},
{"learn":[19.52154121],"iteration":556,"passed_time":1.366575502,"remaining_time":1.086881413},
{"learn":[19.50412716],"iteration":557,"passed_time":1.368266488,"remaining_time":1.083823993},
{"learn":[19.47805361],"iteration":558,"passed_time":1.369945962,"remaining_time":1.080762378},
{"learn":[19.4612293],"iteration":559,"passed_time":1.371661261,"remaining_time":1.077733848},
{"learn":[19.43395031],"iteration":560,"passed_time":1.373296901,"remaining_time":1.074647664},
{"learn":[19.39189888],"iteration":561,"passed_time":1.375045449,"remaining_time":1.071654638},
{"learn":[19.37383897],"iteration":562,"passed_time":1.376636224,"remaining_time":1.06854357},
{"learn":[19.37041155],"iteration":563,"passed_time":1.378255589,"remaining_time":1.065459994},
{"learn":[19.34348543],"iteration":564,"passed_time":1.379901698,"remaining_time":1.062402192},
{"learn":[19.31689513],"iteration":565,"passed_time":1.381600238,"remaining_time":1.059389582},
{"learn":[19.29768508],"iteration":566,"passed_time":1.383457173,"remaining_time":1.056502567},
{"learn":[19.27727095],"iteration":567,"passed_time":1.385146399,"remaining_time":1.053491627},
{"learn":[19.2387233],"iteration":568,"passed_time":1.387000482,"remaining_time":1.050610207},
{"learn":[19.20789148],"iteration":569,"passed_time":1.389086364,"remaining_time":1.047907257},
{"learn":[19.18495362],"iteration":570,"passed_time":1.390907194,"remaining_time":1.045007332},
{"learn":[19.16635622],"iteration":571,"passed_time":1.392702032,"remaining_time":1.042091731},
{"learn":[19.13876486],"iteration":572,"passed_time":1.394880836,"remaining_time":1.039466172},
{"learn":[19.12217604],"iteration":573,"passed_time":1.396644839,"remaining_time":1.036534323},
{"learn":[19.09194955],"iteration":574,"passed_time":1.398183726,"remaining_time":1.033440146},
{"learn":[19.06455511],"iteration":575,"passed_time":1.399771227,"remaining_time":1.030387153},
{"learn":[19.03284254],"iteration":576,"passed_time":1.401254616,"remaining_time":1.027262916},
{"learn":[19.02607699],"iteration":577,"passed_time":1.403151216,"remaining_time":1.024446043},
{"learn":[19.00292319],"iteration":578,"passed_time":1.405248249,"remaining_time":1.021778088},
{"learn":[18.97748558],"iteration":579,"passed_time":1.407488365,"remaining_time":1.019215712},
{"learn":[18.95147897],"iteration":580,"passed_time":1.409153545,"remaining_time":1.01623982},
{"learn":[18.92601639],"iteration":581,"passed_time":1.410854127,"remaining_time":1.013293857},
{"learn":[18.8953771],"iteration":582,"passed_time":1.412525373,"remaining_time":1.010331185},
{"learn":[18.87611397],"iteration":583,"passed_time":1.414172944,"remaining_time":1.007356069},
{"learn":[18.85120822],"iteration":584,"passed_time":1.415719933,"remaining_time":1.00431414},
{"learn":[18.82053617],"iteration":585,"passed_time":1.417473697,"remaining_time":1.001423397},
{"learn":[18.77474956],"iteration":586,"passed_time":1.419303041,"remaining_time":0.9985897038},
{"learn":[18.7440258],"iteration":587,"passed_time":1.420981194,"remaining_time":0.9956534896},
{"learn":[18.71772815],"iteration":588,"passed_time":1.422641414,"remaining_time":0.9927090345},
{"learn":[18.70233821],"iteration":589,"passed_time":1.424150435,"remaining_time":0.9896638614},
{"learn":[18.6831486],"iteration":590,"passed_time":1.425793028,"remaining_time":0.9867163253},
{"learn":[18.6502226],"iteration":591,"passed_time":1.427453474,"remaining_time":0.9837855022},
{"learn":[18.63537643],"iteration":592,"passed_time":1.429028697,"remaining_time":0.9808004713},
{"learn":[18.60842133],"iteration":593,"passed_time":1.430831186,"remaining_time":0.9779755241},
{"learn":[18.58269301],"iteration":594,"passed_time":1.432581703,"remaining_time":0.9751186381},
{"learn":[18.57043537],"iteration":595,"passed_time":1.434386263,"remaining_time":0.9723020976},
{"learn":[18.54597359],"iteration":596,"passed_time":1.436103028,"remaining_time":0.9694296821},
{"learn":[18.53265917],"iteration":597,"passed_time":1.437953115,"remaining_time":0.966650756},
{"learn":[18.50362883],"iteration":598,"passed_time":1.439742223,"remaining_time":0.9638341093},
{"learn":[18.4734864],"iteration":599,"passed_time":1.441174382,"remaining_time":0.9607829215},
{"learn":[18.45629932],"iteration":600,"passed_time":1.442788993,"remaining_time":0.9578582501},
{"learn":[18.43026338],"iteration":601,"passed_time":1.444622049,"remaining_time":0.9550823516},
{"learn":[18.39456799],"iteration":602,"passed_time":1.446246735,"remaining_time":0.9521723941},
{"learn":[18.38583203],"iteration":603,"passed_time":1.447837003,"remaining_time":0.9492441277},
{"learn":[18.35902917],"iteration":604,"passed_time":1.449604534,"remaining_time":0.946436018},
{"learn":[18.33617578],"iteration":605,"passed_time":1.451374705,"remaining_time":0.9436330588},
{"learn":[18.31476457],"iteration":606,"passed_time":1.453173893,"remaining_time":0.9408522901},
{"learn":[18.28643253],"iteration":607,"passed_time":1.454818527,"remaining_time":0.9379751029},
{"learn":[18.26699088],"iteration":608,"passed_time":1.456792611,"remaining_time":0.9353134823},
{"learn":[18.23280949],"iteration":609,"passed_time":1.458570862,"remaining_time":0.9325289116},
{"learn":[18.20756929],"iteration":610,"passed_time":1.460305098,"remaining_time":0.9297196121},
{"learn":[18.18021739],"iteration":611,"passed_time":1.462184732,"remaining_time":0.9270060065},
{"learn":[18.15498691],"iteration":612,"passed_time":1.463921658,"remaining_time":0.924205027},
{"learn":[18.12064518],"iteration":613,"passed_time":1.465549382,"remaining_time":0.9213388626},
{"learn":[18.08967758],"iteration":614,"passed_time":1.467363567,"remaining_time":0.9185934526},
{"learn":[18.06897904],"iteration":615,"passed_time":1.4692797,"remaining_time":0.915914618},
{"learn":[18.04413167],"iteration":616,"passed_time":1.470997047,"remaining_time":0.9131148606},
{"learn":[18.01157403],"iteration":617,"passed_time":1.472722836,"remaining_time":0.9103238241},
{"learn":[17.99512581],"iteration":618,"passed_time":1.474503363,"remaining_time":0.9075699216},
{"learn":[17.98004119],"iteration":619,"passed_time":1.476579844,"remaining_time":0.9050005497},
{"learn":[17.95963824],"iteration":620,"passed_time":1.478114077,"remaining_time":0.9021018281},
{"learn":[17.94559055],"iteration":621,"passed_time":1.479925467,"remaining_time":0.8993759267},
{"learn":[17.91534444],"iteration":622,"passed_time":1.481718723,"remaining_time":0.8966419883},
{"learn":[17.89478205],"iteration":623,"passed_time":1.483441862,"remaining_time":0.8938688142},
{"learn":[17.86580172],"iteration":624,"passed_time":1.485246814,"remaining_time":0.8911480884},
{"learn":[17.85545262],"iteration":625,"passed_time":1.486952764,"remaining_time":0.8883711401},
{"learn":[17.82732068],"iteration":626,"passed_time":1.488894386,"remaining_time":0.8857378086},
{"learn":[17.79384197],"iteration":627,"passed_time":1.490860572,"remaining_time":0.8831212303},
{"learn":[17.76240496],"iteration":628,"passed_time":1.492630193,"remaining_time":0.8803907817},
{"learn":[17.73759998],"iteration":629,"passed_time":1.49457756,"remaining_time":0.8777677733},
{"learn":[17.7160463],"iteration":630,"passed_time":1.496514833,"remaining_time":0.8751410039},
{"learn":[17.68533177],"iteration":631,"passed_time":1.498365746,"remaining_time":0.8724661308},
{"learn":[17.66339934],"iteration":632,"passed_time":1.500118404,"remaining_time":0.8697368948},
{"learn":[17.65422315],"iteration":633,"passed_time":1.501979147,"remaining_time":0.8670731352},
{"learn":[17.64058517],"iteration":634,"passed_time":1.503847302,"remaining_time":0.8644161655},
{"learn":[17.5883087],"iteration":635,"passed_time":1.505802272,"remaining_time":0.8618113635},
{"learn":[17.57312876],"iteration":636,"passed_time":1.507637464,"remaining_time":0.8591403445},
{"learn":[17.55101564],"iteration":637,"passed_time":1.509226166,"remaining_time":0.8563320881},
{"learn":[17.53095912],"iteration":638,"passed_time":1.510938021,"remaining_time":0.8535972233},
{"learn":[17.50956905],"iteration":639,"passed_time":1.512661129,"remaining_time":0.8508718851},
{"learn":[17.48740435],"iteration":640,"passed_time":1.514739946,"remaining_time":0.8483488932},
{"learn":[17.46915218],"iteration":641,"passed_time":1.516686063,"remaining_time":0.8457532874},
{"learn":[17.45139268],"iteration":642,"passed_time":1.518536309,"remaining_time":0.8431064732},
{"learn":[17.40641056],"iteration":643,"passed_time":1.520182116,"remaining_time":0.8403491201},
{"learn":[17.3679404],"iteration":644,"passed_time":1.522010776,"remaining_time":0.8376958535},
{"learn":[17.33229412],"iteration":645,"passed_time":1.523633266,"remaining_time":0.8349321613},
{"learn":[17.29371472],"iteration":646,"passed_time":1.525232341,"remaining_time":0.8321592216},
{"learn":[17.27472617],"iteration":647,"passed_time":1.526734131,"remaining_time":0.829337059},
{"learn":[17.26135412],"iteration":648,"passed_time":1.528388015,"remaining_time":0.8266012223},
{"learn":[17.24956026],"iteration":649,"passed_time":1.53056246,"remaining_time":0.8241490169},
{"learn":[17.21907663],"iteration":650,"passed_time":1.532435623,"remaining_time":0.8215361483},
{"learn":[17.19998808],"iteration":651,"passed_time":1.534336171,"remaining_time":0.818940165},
{"learn":[17.1919799],"iteration":652,"passed_time":1.536135991,"remaining_time":0.8162927857},
{"learn":[17.16916113],"iteration":653,"passed_time":1.537609038,"remaining_time":0.8134751177},
{"learn":[17.14458966],"iteration":654,"passed_time":1.539179069,"remaining_time":0.8107126393},
{"learn":[17.12947148],"iteration":655,"passed_time":1.54077972,"remaining_time":0.8079698531},
{"learn":[17.09924194],"iteration":656,"passed_time":1.542230698,"remaining_time":0.805152404},
{"learn":[17.06365229],"iteration":657,"passed_time":1.543686714,"remaining_time":0.8023417266},
{"learn":[17.04402217],"iteration":658,"passed_time":1.545372396,"remaining_time":0.7996540018},
{"learn":[17.01368659],"iteration":659,"passed_time":1.547155387,"remaining_time":0.7970194416},
{"learn":[16.99384404],"iteration":660,"passed_time":1.549034378,"remaining_time":0.7944366931},
{"learn":[16.97556563],"iteration":661,"passed_time":1.550752725,"remaining_time":0.7917740498},
{"learn":[16.95724928],"iteration":662,"passed_time":1.552627687,"remaining_time":0.7891938623},
{"learn":[16.93757471],"iteration":663,"passed_time":1.554355688,"remaining_time":0.7865414326},
{"learn":[16.91452671],"iteration":664,"passed_time":1.556164021,"remaining_time":0.7839322511},
{"learn":[16.89070718],"iteration":665,"passed_time":1.557725808,"remaining_time":0.7812018315},
{"learn":[16.87057643],"iteration":666,"passed_time":1.559502483,"remaining_time":0.778582199},
{"learn":[16.85565892],"iteration":667,"passed_time":1.561328761,"remaining_time":0.7759897434},
{"learn":[16.82954662],"iteration":668,"passed_time":1.563123629,"remaining_time":0.7733840377},
{"learn":[16.79639926],"iteration":669,"passed_time":1.56503017,"remaining_time":0.7708357555},
{"learn":[16.76989183],"iteration":670,"passed_time":1.566647955,"remaining_time":0.7681478049},
{"learn":[16.75297974],"iteration":671,"passed_time":1.568138154,"remaining_time":0.7654007655},
{"learn":[16.73386868],"iteration":672,"passed_time":1.569793159,"remaining_time":0.7627375381},
{"learn":[16.70990756],"iteration":673,"passed_time":1.571339929,"remaining_time":0.760024951},
{"learn":[16.68115793],"iteration":674,"passed_time":1.572760775,"remaining_time":0.757255188},
{"learn":[16.65764394],"iteration":675,"passed_time":1.574386535,"remaining_time":0.7545876293},
{"learn":[16.65495509],"iteration":676,"passed_time":1.575962178,"remaining_time":0.7518992369},
{"learn":[16.62839363],"iteration":677,"passed_time":1.578029572,"remaining_time":0.7494476729},
{"learn":[16.59513288],"iteration":678,"passed_time":1.580044439,"remaining_time":0.746972408},
{"learn":[16.5635013],"iteration":679,"passed_time":1.581491421,"remaining_time":0.7442312567},
{"learn":[16.54515253],"iteration":680,"passed_time":1.583154901,"remaining_time":0.7415953206},
{"learn":[16.51607894],"iteration":681,"passed_time":1.584894594,"remaining_time":0.7389977726},
{"learn":[16.50216578],"iteration":682,"passed_time":1.586431646,"remaining_time":0.7363086849},
{"learn":[16.48244565],"iteration":683,"passed_time":1.588079079,"remaining_time":0.7336739606},
{"learn":[16.46352499],"iteration":684,"passed_time":1.58940849,"remaining_time":0.730895875},
{"learn":[16.43753165],"iteration":685,"passed_time":1.590930874,"remaining_time":0.7282103416},
{"learn":[16.42686329],"iteration":686,"passed_time":1.59257698,"remaining_time":0.7255845628},
{"learn":[16.41280515],"iteration":687,"passed_time":1.594120706,"remaining_time":0.7229152039},
{"learn":[16.3974918],"iteration":688,"passed_time":1.595878598,"remaining_time":0.7203457824},
{"learn":[16.37557338],"iteration":689,"passed_time":1.597665405,"remaining_time":0.7177917038},
{"learn":[16.36216123],"iteration":690,"passed_time":1.599303113,"remaining_time":0.7151731723},
{"learn":[16.34485154],"iteration":691,"passed_time":1.600787754,"remaining_time":0.7124893472},
{"learn":[16.3291363],"iteration":692,"passed_time":1.602259292,"remaining_time":0.7098031786},
{"learn":[16.32132312],"iteration":693,"passed_time":1.603864363,"remaining_time":0.7071793878},
{"learn":[16.30388567],"iteration":694,"passed_time":1.605399536,"remaining_time":0.7045278537},
{"learn":[16.28566095],"iteration":695,"passed_time":1.607043651,"remaining_time":0.7019271118},
{"learn":[16.26301172],"iteration":696,"passed_time":1.608826702,"remaining_time":0.6993895132},
{"learn":[16.23098197],"iteration":697,"passed_time":1.610534967,"remaining_time":0.6968217191},
{"learn":[16.21776727],"iteration":698,"passed_time":1.612153304,"remaining_time":0.6942176601},
{"learn":[16.19802709],"iteration":699,"passed_time":1.613701796,"remaining_time":0.6915864839},
{"learn":[16.1737876],"iteration":700,"passed_time":1.615277924,"remaining_time":0.6889701845},
{"learn":[16.15169629],"iteration":701,"passed_time":1.61687408,"remaining_time":0.6863653502},
{"learn":[16.12677865],"iteration":702,"passed_time":1.618516456,"remaining_time":0.6837829124},
{"learn":[16.10209441],"iteration":703,"passed_time":1.61993696,"remaining_time":0.6811098581},
{"learn":[16.08181337],"iteration":704,"passed_time":1.621585194,"remaining_time":0.6785356485},
{"learn":[16.0631559],"iteration":705,"passed_time":1.623242757,"remaining_time":0.675967947},
{"learn":[16.03626058],"iteration":706,"passed_time":1.624831546,"remaining_time":0.6733743181},
{"learn":[16.02284333],"iteration":707,"passed_time":1.626676108,"remaining_time":0.6708890161},
{"learn":[16.01724997],"iteration":708,"passed_time":1.628262787,"remaining_time":0.6682996772},
{"learn":[16.0001482],"iteration":709,"passed_time":1.629881918,"remaining_time":0.6657264171},
{"learn":[15.96899885],"iteration":710,"passed_time":1.63155713,"remaining_time":0.6631786365},
{"learn":[15.93353315],"iteration":711,"passed_time":1.633128901,"remaining_time":0.6605914657},
{"learn":[15.9042208],"iteration":712,"passed_time":1.634760521,"remaining_time":0.6580312334},
{"learn":[15.87494069],"iteration":713,"passed_time":1.636237771,"remaining_time":0.6554117683},
{"learn":[15.86523253],"iteration":714,"passed_time":1.637746948,"remaining_time":0.6528082238},
{"learn":[15.84366784],"iteration":715,"passed_time":1.639600876,"remaining_time":0.6503444816},
{"learn":[15.81665612],"iteration":716,"passed_time":1.641289075,"remaining_time":0.6478170266},
{"learn":[15.78631428],"iteration":717,"passed_time":1.64336005,"remaining_time":0.6454422479},
{"learn":[15.76766418],"iteration":718,"passed_time":1.645082646,"remaining_time":0.6429321608},
{"learn":[15.75138932],"iteration":719,"passed_time":1.646831415,"remaining_time":0.6404344391},
{"learn":[15.71632042],"iteration":720,"passed_time":1.6484697,"remaining_time":0.637896042},
{"learn":[15.68857757],"iteration":721,"passed_time":1.650183659,"remaining_time":0.635389276},
{"learn":[15.6687116],"iteration":722,"passed_time":1.651888096,"remaining_time":0.6328810548},
{"learn":[15.64255257],"iteration":723,"passed_time":1.653642756,"remaining_time":0.6303941999},
{"learn":[15.63870008],"iteration":724,"passed_time":1.655504346,"remaining_time":0.6279499242},
{"learn":[15.62379428],"iteration":725,"passed_time":1.658010752,"remaining_time":0.6257506145},
{"learn":[15.6085821],"iteration":726,"passed_time":1.660026972,"remaining_time":0.6233663869},
{"learn":[15.57761273],"iteration":727,"passed_time":1.661760917,"remaining_time":0.6208777054},
{"learn":[15.56182353],"iteration":728,"passed_time":1.663434523,"remaining_time":0.6183686637},
{"learn":[15.54506327],"iteration":729,"passed_time":1.664941699,"remaining_time":0.6158003545},
{"learn":[15.51766005],"iteration":730,"passed_time":1.666488,"remaining_time":0.6132493463},
{"learn":[15.49370633],"iteration":731,"passed_time":1.668153192,"remaining_time":0.6107446112},
{"learn":[15.46851937],"iteration":732,"passed_time":1.670111941,"remaining_time":0.6083490972},
{"learn":[15.45432583],"iteration":733,"passed_time":1.671951715,"remaining_time":0.6059116569},
{"learn":[15.43108454],"iteration":734,"passed_time":1.673855677,"remaining_time":0.6034989855},
{"learn":[15.41304524],"iteration":735,"passed_time":1.675831336,"remaining_time":0.6011134142},
{"learn":[15.40069433],"iteration":736,"passed_time":1.677683231,"remaining_time":0.5986847892},
{"learn":[15.36841586],"iteration":737,"passed_time":1.679328449,"remaining_time":0.5961843546},
{"learn":[15.35862134],"iteration":738,"passed_time":1.680852725,"remaining_time":0.5936435201},
{"learn":[15.34578715],"iteration":739,"passed_time":1.682290328,"remaining_time":0.5910749801},
{"learn":[15.33520998],"iteration":740,"passed_time":1.683677943,"remaining_time":0.5884920207},
{"learn":[15.29467173],"iteration":741,"passed_time":1.685154979,"remaining_time":0.5859433755},
{"learn":[15.2818709],"iteration":742,"passed_time":1.68708794,"remaining_time":0.5835553169},
{"learn":[15.27022373],"iteration":743,"passed_time":1.688814778,"remaining_time":0.5810975581},
{"learn":[15.2486234],"iteration":744,"passed_time":1.690435111,"remaining_time":0.5786053064},
{"learn":[15.24173253],"iteration":745,"passed_time":1.69191647,"remaining_time":0.5760680744},
{"learn":[15.22474123],"iteration":746,"passed_time":1.693651376,"remaining_time":0.5736195424},
{"learn":[15.21351675],"iteration":747,"passed_time":1.695217058,"remaining_time":0.5711159074},
{"learn":[15.19456199],"iteration":748,"passed_time":1.696982819,"remaining_time":0.5686818258},
{"learn":[15.17954973],"iteration":749,"passed_time":1.698664826,"remaining_time":0.5662216088},
{"learn":[15.1654913],"iteration":750,"passed_time":1.700331141,"remaining_time":0.5637582612},
{"learn":[15.15477941],"iteration":751,"passed_time":1.702099348,"remaining_time":0.5613306361},
{"learn":[15.14742548],"iteration":752,"passed_time":1.704184974,"remaining_time":0.5590088826},
{"learn":[15.1275916],"iteration":753,"passed_time":1.706048923,"remaining_time":0.5566154312},
{"learn":[15.10705352],"iteration":754,"passed_time":1.70765737,"remaining_time":0.5541404709},
{"learn":[15.07206003],"iteration":755,"passed_time":1.709247428,"remaining_time":0.5516618684},
{"learn":[15.05039005],"iteration":756,"passed_time":1.71084332,"remaining_time":0.5491874858},
{"learn":[15.03135068],"iteration":757,"passed_time":1.712306035,"remaining_time":0.5466729029},
{"learn":[15.00730037],"iteration":758,"passed_time":1.713854115,"remaining_time":0.5441881971},
{"learn":[14.99853468],"iteration":759,"passed_time":1.715474169,"remaining_time":0.5417286849},
{"learn":[14.99232755],"iteration":760,"passed_time":1.71705513,"remaining_time":0.5392591014},
{"learn":[14.99104364],"iteration":761,"passed_time":1.718754621,"remaining_time":0.5368288711},
{"learn":[14.969862],"iteration":762,"passed_time":1.720528555,"remaining_time":0.5344236796},
{"learn":[14.93919132],"iteration":763,"passed_time":1.722630522,"remaining_time":0.53212147},
{"learn":[14.92929243],"iteration":764,"passed_time":1.72434485,"remaining_time":0.5297007057},
{"learn":[14.9055659],"iteration":765,"passed_time":1.726131019,"remaining_time":0.5273037316},
{"learn":[14.88484762],"iteration":766,"passed_time":1.727833422,"remaining_time":0.5248829039},
{"learn":[14.87000429],"iteration":767,"passed_time":1.729555985,"remaining_time":0.5224700371},
{"learn":[14.86907106],"iteration":768,"passed_time":1.731283949,"remaining_time":0.5200605881},
{"learn":[14.84654485],"iteration":769,"passed_time":1.733288691,"remaining_time":0.5177355831},
{"learn":[14.82259605],"iteration":770,"passed_time":1.735873656,"remaining_time":0.5155837449},
{"learn":[14.78903427],"iteration":771,"passed_time":1.737657894,"remaining_time":0.5131943002},
{"learn":[14.77396846],"iteration":772,"passed_time":1.739545838,"remaining_time":0.510836876},
{"learn":[14.76850505],"iteration":773,"passed_time":1.741314665,"remaining_time":0.508445884},
{"learn":[14.76354011],"iteration":774,"passed_time":1.742723957,"remaining_time":0.5059521164},
{"learn":[14.74499599],"iteration":775,"passed_time":1.744196107,"remaining_time":0.5034792887},
{"learn":[14.72432019],"iteration":776,"passed_time":1.74577633,"remaining_time":0.5010400536},
{"learn":[14.70763051],"iteration":777,"passed_time":1.747380931,"remaining_time":0.4986099829},
{"learn":[14.69234543],"iteration":778,"passed_time":1.74899254,"remaining_time":0.4961840197},
{"learn":[14.67530803],"iteration":779,"passed_time":1.750893404,"remaining_time":0.4938417294},
{"learn":[14.67059705],"iteration":780,"passed_time":1.75267917,"remaining_time":0.4914682949},
{"learn":[14.65896716],"iteration":781,"passed_time":1.754458591,"remaining_time":0.4890945944},
{"learn":[14.63802653],"iteration":782,"passed_time":1.756224441,"remaining_time":0.4867186511},
{"learn":[14.63478442],"iteration":783,"passed_time":1.757752977,"remaining_time":0.4842788813},
{"learn":[14.6129688],"iteration":784,"passed_time":1.759461788,"remaining_time":0.4818908081},
{"learn":[14.59375205],"iteration":785,"passed_time":1.761074526,"remaining_time":0.4794783061},
{"learn":[14.58177357],"iteration":786,"passed_time":1.762691567,"remaining_time":0.4770690011},
{"learn":[14.55226801],"iteration":787,"passed_time":1.764430404,"remaining_time":0.4746944742},
{"learn":[14.54146694],"iteration":788,"passed_time":1.766258726,"remaining_time":0.4723454895},
{"learn":[14.52319183],"iteration":789,"passed_time":1.767874967,"remaining_time":0.4699414468},
{"learn":[14.50542325],"iteration":790,"passed_time":1.769776092,"remaining_time":0.4676146691},
{"learn":[14.48099193],"iteration":791,"passed_time":1.771362181,"remaining_time":0.4652062295},
{"learn":[14.47579469],"iteration":792,"passed_time":1.773061436,"remaining_time":0.4628294038},
{"learn":[14.46016518],"iteration":793,"passed_time":1.77481678,"remaining_time":0.4604688371},
{"learn":[14.43779904],"iteration":794,"passed_time":1.776552889,"remaining_time":0.4581048331},
{"learn":[14.41468063],"iteration":795,"passed_time":1.77813389,"remaining_time":0.4557026552},
{"learn":[14.39734409],"iteration":796,"passed_time":1.779685787,"remaining_time":0.4532951252},
{"learn":[14.38320658],"iteration":797,"passed_time":1.781352384,"remaining_time":0.4509187738},
{"learn":[14.38143399],"iteration":798,"passed_time":1.783026731,"remaining_time":0.4485461489},
{"learn":[14.36932638],"iteration":799,"passed_time":1.78465892,"remaining_time":0.44616473},
{"learn":[14.34860923],"iteration":800,"passed_time":1.78617677,"remaining_time":0.4437567755},
{"learn":[14.33383846],"iteration":801,"passed_time":1.787656403,"remaining_time":0.4413416058},
{"learn":[14.31525544],"iteration":802,"passed_time":1.789688442,"remaining_time":0.4390642877},
{"learn":[14.29991993],"iteration":803,"passed_time":1.791309386,"remaining_time":0.4366873629},
{"learn":[14.29679576],"iteration":804,"passed_time":1.792897055,"remaining_time":0.4343042556},
{"learn":[14.28239439],"iteration":805,"passed_time":1.794543414,"remaining_time":0.4319372486},
{"learn":[14.26487738],"iteration":806,"passed_time":1.795944512,"remaining_time":0.4295133716},
{"learn":[14.24479023],"iteration":807,"passed_time":1.797644539,"remaining_time":0.4271630587},
{"learn":[14.23454448],"iteration":808,"passed_time":1.799339312,"remaining_time":0.4248131131},
{"learn":[14.22052992],"iteration":809,"passed_time":1.801086885,"remaining_time":0.4224771705},
{"learn":[14.19761406],"iteration":810,"passed_time":1.802657673,"remaining_time":0.4201014799},
{"learn":[14.1922611],"iteration":811,"passed_time":1.804227204,"remaining_time":0.4177274808},
{"learn":[14.18526836],"iteration":812,"passed_time":1.805712826,"remaining_time":0.4153361604},
{"learn":[14.16561007],"iteration":813,"passed_time":1.807301114,"remaining_time":0.4129705247},
{"learn":[14.14070375],"iteration":814,"passed_time":1.809023252,"remaining_time":0.4106371799},
{"learn":[14.11566157],"iteration":815,"passed_time":1.810815193,"remaining_time":0.408321073},
{"learn":[14.10132219],"iteration":816,"passed_time":1.812461859,"remaining_time":0.4059737089},
{"learn":[14.09214524],"iteration":817,"passed_time":1.814219065,"remaining_time":0.4036526527},
{"learn":[14.06366033],"iteration":818,"passed_time":1.816099694,"remaining_time":0.4013602499},
{"learn":[14.04767394],"iteration":819,"passed_time":1.817828821,"remaining_time":0.3990355949},
{"learn":[14.02913353],"iteration":820,"passed_time":1.819536621,"remaining_time":0.3967077408},
{"learn":[14.01312831],"iteration":821,"passed_time":1.820961404,"remaining_time":0.3943201095},
{"learn":[14.00025671],"iteration":822,"passed_time":1.822549737,"remaining_time":0.3919699921},
{"learn":[13.97339173],"iteration":823,"passed_time":1.824040628,"remaining_time":0.3896009108},
{"learn":[13.95513971],"iteration":824,"passed_time":1.825555323,"remaining_time":0.3872390078},
{"learn":[13.93498008],"iteration":825,"passed_time":1.827057357,"remaining_time":0.3848764892},
{"learn":[13.91920906],"iteration":826,"passed_time":1.829137529,"remaining_time":0.3826369921},
{"learn":[13.90621198],"iteration":827,"passed_time":1.831180609,"remaining_time":0.3803901748},
{"learn":[13.88499464],"iteration":828,"passed_time":1.832774496,"remaining_time":0.3780511929},
{"learn":[13.86234918],"iteration":829,"passed_time":1.834466789,"remaining_time":0.3757341617},
{"learn":[13.84139405],"iteration":830,"passed_time":1.83612241,"remaining_time":0.3734111761},
{"learn":[13.82920246],"iteration":831,"passed_time":1.838033531,"remaining_time":0.3711413861},
{"learn":[13.81417144],"iteration":832,"passed_time":1.839610759,"remaining_time":0.3688055183},
{"learn":[13.79108096],"iteration":833,"passed_time":1.841534297,"remaining_time":0.3665403997},
{"learn":[13.7785887],"iteration":834,"passed_time":1.843159636,"remaining_time":0.3642171735},
{"learn":[13.7760854],"iteration":835,"passed_time":1.844843416,"remaining_time":0.3619070816},
{"learn":[13.76901733],"iteration":836,"passed_time":1.846565848,"remaining_time":0.3596060134},
{"learn":[13.74255509],"iteration":837,"passed_time":1.848374575,"remaining_time":0.3573230086},
{"learn":[13.73816611],"iteration":838,"passed_time":1.849988765,"remaining_time":0.3550038035},
{"learn":[13.72419515],"iteration":839,"passed_time":1.851505018,"remaining_time":0.3526676224},
{"learn":[13.70049778],"iteration":840,"passed_time":1.852981566,"remaining_time":0.3503258847},
{"learn":[13.67763601],"iteration":841,"passed_time":1.854641218,"remaining_time":0.348020561},
{"learn":[13.66129251],"iteration":842,"passed_time":1.856355687,"remaining_time":0.3457269786},
{"learn":[13.65307156],"iteration":843,"passed_time":1.858084906,"remaining_time":0.3434374945},
{"learn":[13.6251342],"iteration":844,"passed_time":1.859935606,"remaining_time":0.3411716201},
{"learn":[13.59438192],"iteration":845,"passed_time":1.862025746,"remaining_time":0.3389503132},
{"learn":[13.58007099],"iteration":846,"passed_time":1.86361513,"remaining_time":0.3366388606},
{"learn":[13.54540183],"iteration":847,"passed_time":1.86531933,"remaining_time":0.3343496912},
{"learn":[13.5216915],"iteration":848,"passed_time":1.866915453,"remaining_time":0.3320426778},
{"learn":[13.50284031],"iteration":849,"passed_time":1.868494953,"remaining_time":0.3297344035},
{"learn":[13.48962164],"iteration":850,"passed_time":1.870172493,"remaining_time":0.3274450076},
{"learn":[13.46926174],"iteration":851,"passed_time":1.871694262,"remaining_time":0.3251299892},
{"learn":[13.46656476],"iteration":852,"passed_time":1.873154272,"remaining_time":0.3228061875},
{"learn":[13.44788503],"iteration":853,"passed_time":1.874677603,"remaining_time":0.3204952342},
{"learn":[13.42689144],"iteration":854,"passed_time":1.876384082,"remaining_time":0.3182171836},
{"learn":[13.39735307],"iteration":855,"passed_time":1.878032266,"remaining_time":0.3159306616},
{"learn":[13.37439491],"iteration":856,"passed_time":1.879885695,"remaining_time":0.3136798767},
{"learn":[13.36169674],"iteration":857,"passed_time":1.881646791,"remaining_time":0.3114147371},
{"learn":[13.33161608],"iteration":858,"passed_time":1.883169151,"remaining_time":0.3091115835},
{"learn":[13.31386792],"iteration":859,"passed_time":1.884852531,"remaining_time":0.3068364585},
{"learn":[13.29552919],"iteration":860,"passed_time":1.886463263,"remaining_time":0.3045509798},
{"learn":[13.27691054],"iteration":861,"passed_time":1.88808227,"remaining_time":0.3022683912},
{"learn":[13.25938014],"iteration":862,"passed_time":1.889722704,"remaining_time":0.2999907421},
{"learn":[13.23571803],"iteration":863,"passed_time":1.891196849,"remaining_time":0.2976883929},
{"learn":[13.22359148],"iteration":864,"passed_time":1.892925316,"remaining_time":0.2954276505},
{"learn":[13.2041771],"iteration":865,"passed_time":1.894577614,"remaining_time":0.2931563514},
{"learn":[13.19084015],"iteration":866,"passed_time":1.896206187,"remaining_time":0.2908828407},
{"learn":[13.18539894],"iteration":867,"passed_time":1.897749182,"remaining_time":0.2885978019},
{"learn":[13.17182169],"iteration":868,"passed_time":1.899205457,"remaining_time":0.286301398},
{"learn":[13.16104019],"iteration":869,"passed_time":1.900711961,"remaining_time":0.284014431},
{"learn":[13.13744109],"iteration":870,"passed_time":1.902214699,"remaining_time":0.2817286982},
{"learn":[13.11540889],"iteration":871,"passed_time":1.903652918,"remaining_time":0.2794352908},
{"learn":[13.10005247],"iteration":872,"passed_time":1.905435601,"remaining_time":0.2771939533},
{"learn":[13.08569677],"iteration":873,"passed_time":1.907274594,"remaining_time":0.2749617835},
{"learn":[13.07564297],"iteration":874,"passed_time":1.909177845,"remaining_time":0.2727396922},
{"learn":[13.05618801],"iteration":875,"passed_time":1.911342793,"remaining_time":0.2705553725},
{"learn":[13.04446154],"iteration":876,"passed_time":1.912944902,"remaining_time":0.2682921585},
{"learn":[13.02133213],"iteration":877,"passed_time":1.914553247,"remaining_time":0.2660313168},
{"learn":[13.00390338],"iteration":878,"passed_time":1.916261245,"remaining_time":0.2637856776},
{"learn":[12.99305122],"iteration":879,"passed_time":1.917916696,"remaining_time":0.2615340949},
{"learn":[12.97503339],"iteration":880,"passed_time":1.919644882,"remaining_time":0.2592936901},
{"learn":[12.95871505],"iteration":881,"passed_time":1.921546712,"remaining_time":0.257077678},
{"learn":[12.94825852],"iteration":882,"passed_time":1.924104859,"remaining_time":0.2549493415},
{"learn":[12.93179357],"iteration":883,"passed_time":1.926015383,"remaining_time":0.2527350502},
{"learn":[12.90561378],"iteration":884,"passed_time":1.92780922,"remaining_time":0.2505062828},
{"learn":[12.88928209],"iteration":885,"passed_time":1.92958265,"remaining_time":0.2482758714},
{"learn":[12.87449444],"iteration":886,"passed_time":1.931057416,"remaining_time":0.2460084419},
{"learn":[12.86722271],"iteration":887,"passed_time":1.932590318,"remaining_time":0.2437501301},
{"learn":[12.85469147],"iteration":888,"passed_time":1.934269942,"remaining_time":0.2415117701},
{"learn":[12.83833047],"iteration":889,"passed_time":1.935839854,"remaining_time":0.2392611055},
{"learn":[12.82331942],"iteration":890,"passed_time":1.937445742,"remaining_time":0.2370163703},
{"learn":[12.8117134],"iteration":891,"passed_time":1.939504169,"remaining_time":0.2348278591},
{"learn":[12.78770988],"iteration":892,"passed_time":1.941253241,"remaining_time":0.232602572},
{"learn":[12.77383838],"iteration":893,"passed_time":1.943152111,"remaining_time":0.2303961116},
{"learn":[12.76118249],"iteration":894,"passed_time":1.94478826,"remaining_time":0.2281595165},
{"learn":[12.74880534],"iteration":895,"passed_time":1.946318161,"remaining_time":0.2259119295},
{"learn":[12.72337893],"iteration":896,"passed_time":1.94795498,"remaining_time":0.2236782195},
{"learn":[12.7105976],"iteration":897,"passed_time":1.949615408,"remaining_time":0.2214485208},
{"learn":[12.68237778],"iteration":898,"passed_time":1.951182797,"remaining_time":0.2192096357},
{"learn":[12.67108777],"iteration":899,"passed_time":1.952808299,"remaining_time":0.2169786999},
{"learn":[12.65959129],"iteration":900,"passed_time":1.95445184,"remaining_time":0.2147510901},
{"learn":[12.64944892],"iteration":901,"passed_time":1.956304289,"remaining_time":0.2125474727},
{"learn":[12.64719317],"iteration":902,"passed_time":1.958020539,"remaining_time":0.2103300026},
{"learn":[12.61951424],"iteration":903,"passed_time":1.959608594,"remaining_time":0.2081000277},
{"learn":[12.60024915],"iteration":904,"passed_time":1.961260237,"remaining_time":0.2058781465},
{"learn":[12.58744505],"iteration":905,"passed_time":1.96282687,"remaining_time":0.2036487039},
{"learn":[12.58088757],"iteration":906,"passed_time":1.964400945,"remaining_time":0.2014214861},
{"learn":[12.56837042],"iteration":907,"passed_time":1.966131304,"remaining_time":0.1992115418},
{"learn":[12.55503728],"iteration":908,"passed_time":1.967772567,"remaining_time":0.1969937333},
{"learn":[12.53347384],"iteration":909,"passed_time":1.969337052,"remaining_time":0.1947695986},
{"learn":[12.52583875],"iteration":910,"passed_time":1.97104027,"remaining_time":0.1925604655},
{"learn":[12.51645379],"iteration":911,"passed_time":1.972701063,"remaining_time":0.1903483482},
{"learn":[12.50415378],"iteration":912,"passed_time":1.974343296,"remaining_time":0.1881356701},
{"learn":[12.48535158],"iteration":913,"passed_time":1.976020753,"remaining_time":0.1859275544},
{"learn":[12.46786234],"iteration":914,"passed_time":1.977569878,"remaining_time":0.1837086772},
{"learn":[12.44381335],"iteration":915,"passed_time":1.979030341,"remaining_time":0.1814831317},
{"learn":[12.43262614],"iteration":916,"passed_time":1.980567212,"remaining_time":0.1792661708},
{"learn":[12.42090661],"iteration":917,"passed_time":1.982058612,"remaining_time":0.1770466299},
{"learn":[12.40313638],"iteration":918,"passed_time":1.983627503,"remaining_time":0.1748355035},
{"learn":[12.38718173],"iteration":919,"passed_time":1.985370897,"remaining_time":0.1726409476},
{"learn":[12.38554462],"iteration":920,"passed_time":1.986989976,"remaining_time":0.170436708},
{"learn":[12.36860679],"iteration":921,"passed_time":1.988502352,"remaining_time":0.1682247109},
{"learn":[12.35724995],"iteration":922,"passed_time":1.990195549,"remaining_time":0.1660293145},
{"learn":[12.33847854],"iteration":923,"passed_time":1.991890286,"remaining_time":0.1638351318},
{"learn":[12.32133461],"iteration":924,"passed_time":1.993625624,"remaining_time":0.1616453209},
{"learn":[12.31173309],"iteration":925,"passed_time":1.995435727,"remaining_time":0.1594624663},
{"learn":[12.30136925],"iteration":926,"passed_time":1.997146216,"remaining_time":0.1572725714},
{"learn":[12.29456147],"iteration":927,"passed_time":1.998814072,"remaining_time":0.1550804022},
{"learn":[12.27299863],"iteration":928,"passed_time":2.000320408,"remaining_time":0.1528770172},
{"learn":[12.26820863],"iteration":929,"passed_time":2.002166423,"remaining_time":0.1507006985},
{"learn":[12.25858661],"iteration":930,"passed_time":2.003827059,"remaining_time":0.1485113502},
{"learn":[12.2489456],"iteration":931,"passed_time":2.005511365,"remaining_time":0.1463248636},
{"learn":[12.23652776],"iteration":932,"passed_time":2.007269111,"remaining_time":0.1441447271},
{"learn":[12.22680089],"iteration":933,"passed_time":2.009126943,"remaining_time":0.1419725677},
{"learn":[12.20728208],"iteration":934,"passed_time":2.010642615,"remaining_time":0.1397772941},
{"learn":[12.18971579],"iteration":935,"passed_time":2.012306628,"remaining_time":0.1375936156},
{"learn":[12.16501641],"iteration":936,"passed_time":2.014037783,"remaining_time":0.1354155606},
{"learn":[12.1404104],"iteration":937,"passed_time":2.01557043,"remaining_time":0.1332253376},
{"learn":[12.13311389],"iteration":938,"passed_time":2.017063159,"remaining_time":0.1310339219},
{"learn":[12.11821925],"iteration":939,"passed_time":2.01885025,"remaining_time":0.1288627819},
{"learn":[12.10682928],"iteration":940,"passed_time":2.020534348,"remaining_time":0.1266860005},
{"learn":[12.07830328],"iteration":941,"passed_time":2.0220971,"remaining_time":0.1245027939},
{"learn":[12.06226852],"iteration":942,"passed_time":2.023569969,"remaining_time":0.12231547},
{"learn":[12.04993854],"iteration":943,"passed_time":2.025123207,"remaining_time":0.1201344275},
{"learn":[12.03274034],"iteration":944,"passed_time":2.027057965,"remaining_time":0.1179769186},
{"learn":[12.01810635],"iteration":945,"passed_time":2.029169673,"remaining_time":0.1158299813},
{"learn":[12.00450612],"iteration":946,"passed_time":2.030840729,"remaining_time":0.1136584568},
{"learn":[11.9921894],"iteration":947,"passed_time":2.032388137,"remaining_time":0.1114812058},
{"learn":[11.98200121],"iteration":948,"passed_time":2.034154397,"remaining_time":0.1093170435},
{"learn":[11.98133859],"iteration":949,"passed_time":2.035931604,"remaining_time":0.107154295},
{"learn":[11.9674402],"iteration":950,"passed_time":2.037576943,"remaining_time":0.1049855628},
{"learn":[11.95022433],"iteration":951,"passed_time":2.039105253,"remaining_time":0.1028120296},
{"learn":[11.94337897],"iteration":952,"passed_time":2.040743046,"remaining_time":0.1006452499},
{"learn":[11.92903716],"iteration":953,"passed_time":2.042283172,"remaining_time":0.09847486993},
{"learn":[11.90702925],"iteration":954,"passed_time":2.043792228,"remaining_time":0.09630434583},
{"learn":[11.88786836],"iteration":955,"passed_time":2.045469848,"remaining_time":0.0941429637},
{"learn":[11.87981499],"iteration":956,"passed_time":2.04698681,"remaining_time":0.0919753739},
{"learn":[11.87170875],"iteration":957,"passed_time":2.048759322,"remaining_time":0.08982034607},
{"learn":[11.85480918],"iteration":958,"passed_time":2.050311914,"remaining_time":0.08765671373},
{"learn":[11.84373383],"iteration":959,"passed_time":2.051890746,"remaining_time":0.08549544774},
{"learn":[11.83375691],"iteration":960,"passed_time":2.05351999,"remaining_time":0.08333743976},
{"learn":[11.81897548],"iteration":961,"passed_time":2.054880644,"remaining_time":0.08116992147},
{"learn":[11.80554567],"iteration":962,"passed_time":2.056398858,"remaining_time":0.07901013266},
{"learn":[11.78970225],"iteration":963,"passed_time":2.058109393,"remaining_time":0.076858857},
{"learn":[11.77852732],"iteration":964,"passed_time":2.05980274,"remaining_time":0.07470787141},
{"learn":[11.75587451],"iteration":965,"passed_time":2.061346638,"remaining_time":0.07255257317},
{"learn":[11.74561716],"iteration":966,"passed_time":2.062772261,"remaining_time":0.07039450323},
{"learn":[11.73664039],"iteration":967,"passed_time":2.064328616,"remaining_time":0.0682422683},
{"learn":[11.72058683],"iteration":968,"passed_time":2.066059889,"remaining_time":0.06609685919},
{"learn":[11.70433101],"iteration":969,"passed_time":2.067587867,"remaining_time":0.0639460165},
{"learn":[11.69515124],"iteration":970,"passed_time":2.069341198,"remaining_time":0.06180318718},
{"learn":[11.68234243],"iteration":971,"passed_time":2.071039145,"remaining_time":0.05965956385},
{"learn":[11.6728581],"iteration":972,"passed_time":2.072633006,"remaining_time":0.05751396832},
{"learn":[11.65561762],"iteration":973,"passed_time":2.074157964,"remaining_time":0.0553676664},
{"learn":[11.63406714],"iteration":974,"passed_time":2.07575172,"remaining_time":0.05322440307},
{"learn":[11.62124063],"iteration":975,"passed_time":2.07739473,"remaining_time":0.05108347698},
{"learn":[11.61334018],"iteration":976,"passed_time":2.079139964,"remaining_time":0.04894597663},
{"learn":[11.59808539],"iteration":977,"passed_time":2.080763623,"remaining_time":0.04680654367},
{"learn":[11.58477493],"iteration":978,"passed_time":2.082369836,"remaining_time":0.04466779016},
{"learn":[11.57615788],"iteration":979,"passed_time":2.084168542,"remaining_time":0.04253405188},
{"learn":[11.56603814],"iteration":980,"passed_time":2.085777809,"remaining_time":0.04039732759},
{"learn":[11.54587014],"iteration":981,"passed_time":2.087888139,"remaining_time":0.03827086202},
{"learn":[11.53112958],"iteration":982,"passed_time":2.089621178,"remaining_time":0.03613790439},
{"learn":[11.51714242],"iteration":983,"passed_time":2.091033155,"remaining_time":0.03400053911},
{"learn":[11.51027101],"iteration":984,"passed_time":2.092638058,"remaining_time":0.03186758464},
{"learn":[11.50360113],"iteration":985,"passed_time":2.094170105,"remaining_time":0.0297346668},
{"learn":[11.5003941],"iteration":986,"passed_time":2.095645845,"remaining_time":0.02760222491},
{"learn":[11.48930645],"iteration":987,"passed_time":2.097593967,"remaining_time":0.0254768498},
{"learn":[11.47385337],"iteration":988,"passed_time":2.099211231,"remaining_time":0.02334815323},
{"learn":[11.46119133],"iteration":989,"passed_time":2.100993156,"remaining_time":0.02122215309},
{"learn":[11.44340234],"iteration":990,"passed_time":2.102721259,"remaining_time":0.01909635856},
{"learn":[11.43475179],"iteration":991,"passed_time":2.104297175,"remaining_time":0.0169701385},
{"learn":[11.42414271],"iteration":992,"passed_time":2.105975038,"remaining_time":0.01484574548},
{"learn":[11.41298304],"iteration":993,"passed_time":2.107623819,"remaining_time":0.01272207536},
{"learn":[11.41223848],"iteration":994,"passed_time":2.109275781,"remaining_time":0.01059937579},
{"learn":[11.39916984],"iteration":995,"passed_time":2.110762496,"remaining_time":0.008476957814},
{"learn":[11.39856034],"iteration":996,"passed_time":2.112261546,"remaining_time":0.006355852196},
{"learn":[11.38526839],"iteration":997,"passed_time":2.114142576,"remaining_time":0.00423675867},
{"learn":[11.37641933],"iteration":998,"passed_time":2.115857518,"remaining_time":0.002117975494},
{"learn":[11.35088737],"iteration":999,"passed_time":2.117455815,"remaining_time":0}
]}